{"data":[{"BLOCK":"A.Chowki (Td)","Latitude":20.615345,"Longitude":80.585575,"STATE LGD":22,"DISTRICT LGD":761,"BLOCK LGD":3708,"STATE":"Chhattisgarh","DISTRICT":"Mohla-Manpur- A Chowki"},{"BLOCK":"Abu Road","Latitude":24.4645083,"Longitude":72.7230718,"STATE LGD":8,"DISTRICT LGD":115,"BLOCK LGD":781,"STATE":"Rajasthan","DISTRICT":"Sirohi"},{"BLOCK":"Afzalpur","Latitude":17.2014637,"Longitude":76.3543045,"STATE LGD":29,"DISTRICT LGD":538,"BLOCK LGD":5836,"STATE":"Karnataka","DISTRICT":"Kalburgi"},{"BLOCK":"Aheri","Latitude":19.4129162,"Longitude":79.9951388,"STATE LGD":27,"DISTRICT LGD":475,"BLOCK LGD":4371,"STATE":"Maharashtra","DISTRICT":"Gadhichiroli"},{"BLOCK":"Ahore","Latitude":25.371009,"Longitude":72.7688998,"STATE LGD":8,"DISTRICT LGD":104,"BLOCK LGD":700,"STATE":"Rajasthan","DISTRICT":"Jalore"},{"BLOCK":"Ajaigarh","Latitude":24.9041087,"Longitude":80.2495992,"STATE LGD":23,"DISTRICT LGD":420,"BLOCK LGD":3930,"STATE":"Madhya Pradesh","DISTRICT":"Panna"},{"BLOCK":"Ajnala","Latitude":31.8462948,"Longitude":74.7427633,"STATE LGD":3,"DISTRICT LGD":27,"BLOCK LGD":210,"STATE":"Punjab","DISTRICT":"Amritsar"},{"BLOCK":"Akarani","Latitude":21.3692727,"Longitude":74.20613,"STATE LGD":27,"DISTRICT LGD":486,"BLOCK LGD":4474,"STATE":"Maharashtra","DISTRICT":"Nandurbar"},{"BLOCK":"Akkalkot","Latitude":17.5200572,"Longitude":76.1800148,"STATE LGD":27,"DISTRICT LGD":496,"BLOCK LGD":4578,"STATE":"Maharashtra","DISTRICT":"Solapur"},{"BLOCK":"Akkalkuva","Latitude":21.5555886,"Longitude":74.0071936,"STATE LGD":27,"DISTRICT LGD":486,"BLOCK LGD":4473,"STATE":"Maharashtra","DISTRICT":"Nandurbar"},{"BLOCK":"Akuhaito","Latitude":26.0732808,"Longitude":94.4424861,"STATE LGD":13,"DISTRICT LGD":251,"BLOCK LGD":6745,"STATE":"Nagaland","DISTRICT":"Zunheboto"},{"BLOCK":"Alathur","Latitude":11.1282294,"Longitude":78.8287958,"STATE LGD":33,"DISTRICT LGD":581,"BLOCK LGD":6254,"STATE":"Tamil Nadu","DISTRICT":"Perambalur"},{"BLOCK":"Amanpur","Latitude":27.7099549,"Longitude":78.7290894,"STATE LGD":9,"DISTRICT LGD":633,"BLOCK LGD":1064,"STATE":"Uttar Pradesh","DISTRICT":"Kasganj"},{"BLOCK":"Ambiapur","Latitude":28.2164585,"Longitude":78.6745603,"STATE LGD":9,"DISTRICT LGD":133,"BLOCK LGD":999,"STATE":"Uttar Pradesh","DISTRICT":"Budaun"},{"BLOCK":"Amlarem","Latitude":25.2861016,"Longitude":92.1093212,"STATE LGD":17,"DISTRICT LGD":275,"BLOCK LGD":2463,"STATE":"Meghalaya","DISTRICT":"Wjh (Jaintia Region)"},{"BLOCK":"Amri","Latitude":25.9688082,"Longitude":92.2548048,"STATE LGD":18,"DISTRICT LGD":710,"BLOCK LGD":2616,"STATE":"Assam","DISTRICT":"West Karbi Anglong"},{"BLOCK":"Andar","Latitude":26.0994578,"Longitude":84.2815223,"STATE LGD":10,"DISTRICT LGD":222,"BLOCK LGD":2107,"STATE":"Bihar","DISTRICT":"Siwan"},{"BLOCK":"Andimadam","Latitude":11.3298116,"Longitude":79.3429491,"STATE LGD":33,"DISTRICT LGD":610,"BLOCK LGD":6255,"STATE":"Tamil Nadu","DISTRICT":"Ariyalur"},{"BLOCK":"Arithang Chongrang","Latitude":27.3471312,"Longitude":88.2551421,"STATE LGD":11,"DISTRICT LGD":228,"BLOCK LGD":7138,"STATE":"Sikkim","DISTRICT":"Gyalshing"},{"BLOCK":"Asafpur","Latitude":27.8991135,"Longitude":79.4117202,"STATE LGD":9,"DISTRICT LGD":133,"BLOCK LGD":1000,"STATE":"Uttar Pradesh","DISTRICT":"Budaun"},{"BLOCK":"Asmauli","Latitude":28.698016,"Longitude":78.5238503,"STATE LGD":9,"DISTRICT LGD":659,"BLOCK LGD":1412,"STATE":"Uttar Pradesh","DISTRICT":"Sambhal"},{"BLOCK":"Attappadi","Latitude":11.0723285,"Longitude":76.5501591,"STATE LGD":32,"DISTRICT LGD":563,"BLOCK LGD":6048,"STATE":"Kerala","DISTRICT":"Palakkad"},{"BLOCK":"Aurad","Latitude":18.2509225,"Longitude":77.4078655,"STATE LGD":29,"DISTRICT LGD":529,"BLOCK LGD":5788,"STATE":"Karnataka","DISTRICT":"Bidar"},{"BLOCK":"Aurai","Latitude":25.2671682,"Longitude":82.5481688,"STATE LGD":9,"DISTRICT LGD":179,"BLOCK LGD":1511,"STATE":"Uttar Pradesh","DISTRICT":"St Ravidas Nagar"},{"BLOCK":"Awagarh","Latitude":27.4429911,"Longitude":78.4739469,"STATE LGD":9,"DISTRICT LGD":138,"BLOCK LGD":1065,"STATE":"Uttar Pradesh","DISTRICT":"Etah"},{"BLOCK":"Azhutha","Latitude":9.5729163,"Longitude":76.9829606,"STATE LGD":32,"DISTRICT LGD":556,"BLOCK LGD":5977,"STATE":"Kerala","DISTRICT":"Idukki"},{"BLOCK":"Baberu","Latitude":25.5468922,"Longitude":80.6807182,"STATE LGD":9,"DISTRICT LGD":128,"BLOCK LGD":934,"STATE":"Uttar Pradesh","DISTRICT":"Banda"},{"BLOCK":"Babhanjot","Latitude":27.1665182,"Longitude":81.9711901,"STATE LGD":9,"DISTRICT LGD":147,"BLOCK LGD":1153,"STATE":"Uttar Pradesh","DISTRICT":"Gonda"},{"BLOCK":"Badhra","Latitude":28.5100963,"Longitude":75.9293372,"STATE LGD":6,"DISTRICT LGD":701,"BLOCK LGD":453,"STATE":"Haryana","DISTRICT":"Charkhi Dadri"},{"BLOCK":"Badnapur","Latitude":19.8679808,"Longitude":75.714147,"STATE LGD":27,"DISTRICT LGD":479,"BLOCK LGD":4412,"STATE":"Maharashtra","DISTRICT":"Jalna"},{"BLOCK":"Baghauli","Latitude":26.8321288,"Longitude":83.0452502,"STATE LGD":9,"DISTRICT LGD":178,"BLOCK LGD":1501,"STATE":"Uttar Pradesh","DISTRICT":"St Kabir Nagar"},{"BLOCK":"Bahadrabad","Latitude":29.9189257,"Longitude":78.0376912,"STATE LGD":5,"DISTRICT LGD":50,"BLOCK LGD":385,"STATE":"Uttarakhand","DISTRICT":"Haridwar"},{"BLOCK":"Baharia","Latitude":25.6190863,"Longitude":82.0003223,"STATE LGD":9,"DISTRICT LGD":120,"BLOCK LGD":831,"STATE":"Uttar Pradesh","DISTRICT":"Prayagraj"},{"BLOCK":"Baheri","Latitude":28.7792802,"Longitude":79.478788,"STATE LGD":9,"DISTRICT LGD":130,"BLOCK LGD":960,"STATE":"Uttar Pradesh","DISTRICT":"Bareilly"},{"BLOCK":"Baikunthpur","Latitude":23.2785167,"Longitude":82.520734,"STATE LGD":22,"DISTRICT LGD":384,"BLOCK LGD":7144,"STATE":"Chhattisgarh","DISTRICT":"Korea"},{"BLOCK":"Bairgania","Latitude":26.7361192,"Longitude":85.2529188,"STATE LGD":10,"DISTRICT LGD":221,"BLOCK LGD":2090,"STATE":"Bihar","DISTRICT":"Sitamarhi"},{"BLOCK":"Baisi","Latitude":25.864721,"Longitude":87.7361833,"STATE LGD":10,"DISTRICT LGD":214,"BLOCK LGD":1997,"STATE":"Bihar","DISTRICT":"Purnia"},{"BLOCK":"Bajag","Latitude":22.6734298,"Longitude":81.349232,"STATE LGD":23,"DISTRICT LGD":404,"BLOCK LGD":3830,"STATE":"Madhya Pradesh","DISTRICT":"Dindori"},{"BLOCK":"Bajna","Latitude":23.3128284,"Longitude":74.6307384,"STATE LGD":23,"DISTRICT LGD":423,"BLOCK LGD":3949,"STATE":"Madhya Pradesh","DISTRICT":"Ratlam"},{"BLOCK":"Balarampur","Latitude":23.0935695,"Longitude":86.2050796,"STATE LGD":19,"DISTRICT LGD":321,"BLOCK LGD":3046,"STATE":"West Bengal","DISTRICT":"Purulia"},{"BLOCK":"Baldeogarh","Latitude":24.7503126,"Longitude":79.0436803,"STATE LGD":23,"DISTRICT LGD":434,"BLOCK LGD":4027,"STATE":"Madhya Pradesh","DISTRICT":"Tikamgarh"},{"BLOCK":"Balisankara","Latitude":22.3487484,"Longitude":84.0218153,"STATE LGD":21,"DISTRICT LGD":373,"BLOCK LGD":3573,"STATE":"Odisha","DISTRICT":"Sundargarh"},{"BLOCK":"Balrampur","Latitude":25.3332728,"Longitude":87.7386016,"STATE LGD":10,"DISTRICT LGD":201,"BLOCK LGD":1800,"STATE":"Bihar","DISTRICT":"Katihar"},{"BLOCK":"Bamori","Latitude":24.1461942,"Longitude":77.0098652,"STATE LGD":23,"DISTRICT LGD":406,"BLOCK LGD":3844,"STATE":"Madhya Pradesh","DISTRICT":"Guna"},{"BLOCK":"Bankeyganj","Latitude":28.1410821,"Longitude":80.4050005,"STATE LGD":9,"DISTRICT LGD":159,"BLOCK LGD":1294,"STATE":"Uttar Pradesh","DISTRICT":"Kheri"},{"BLOCK":"Bansdih","Latitude":25.8806733,"Longitude":84.2059569,"STATE LGD":9,"DISTRICT LGD":126,"BLOCK LGD":909,"STATE":"Uttar Pradesh","DISTRICT":"Ballia"},{"BLOCK":"Bansgaon","Latitude":26.5534604,"Longitude":83.3373358,"STATE LGD":9,"DISTRICT LGD":148,"BLOCK LGD":1169,"STATE":"Uttar Pradesh","DISTRICT":"Gorakhpur"},{"BLOCK":"Bansjore","Latitude":22.4322641,"Longitude":84.67912,"STATE LGD":20,"DISTRICT LGD":342,"BLOCK LGD":6613,"STATE":"Jharkhand","DISTRICT":"Simdega"},{"BLOCK":"Banspal","Latitude":21.3918387,"Longitude":85.3478553,"STATE LGD":21,"DISTRICT LGD":361,"BLOCK LGD":3444,"STATE":"Odisha","DISTRICT":"Keonjhar"},{"BLOCK":"Barhat","Latitude":25.0225111,"Longitude":86.2507349,"STATE LGD":10,"DISTRICT LGD":198,"BLOCK LGD":1770,"STATE":"Bihar","DISTRICT":"Jamui"},{"BLOCK":"Bariyarpur","Latitude":25.2908973,"Longitude":86.5615169,"STATE LGD":10,"DISTRICT LGD":207,"BLOCK LGD":1870,"STATE":"Bihar","DISTRICT":"Munger"},{"BLOCK":"Basantpur","Latitude":26.4938816,"Longitude":87.0245688,"STATE LGD":10,"DISTRICT LGD":223,"BLOCK LGD":2126,"STATE":"Bihar","DISTRICT":"Supaul"},{"BLOCK":"Baseri","Latitude":26.7463459,"Longitude":77.5301083,"STATE LGD":8,"DISTRICT LGD":98,"BLOCK LGD":666,"STATE":"Rajasthan","DISTRICT":"Dholpur"},{"BLOCK":"Basoda","Latitude":23.8476228,"Longitude":77.9172403,"STATE LGD":23,"DISTRICT LGD":437,"BLOCK LGD":4042,"STATE":"Madhya Pradesh","DISTRICT":"Vidisha"},{"BLOCK":"Behal","Latitude":28.6281316,"Longitude":75.6090259,"STATE LGD":6,"DISTRICT LGD":59,"BLOCK LGD":455,"STATE":"Haryana","DISTRICT":"Bhiwani"},{"BLOCK":"Behea","Latitude":25.5578651,"Longitude":84.4445301,"STATE LGD":10,"DISTRICT LGD":193,"BLOCK LGD":1692,"STATE":"Bihar","DISTRICT":"Bhojpur"},{"BLOCK":"Bhagabangola-1","Latitude":24.329066,"Longitude":88.3063781,"STATE LGD":19,"DISTRICT LGD":319,"BLOCK LGD":3005,"STATE":"West Bengal","DISTRICT":"Murshidabad"},{"BLOCK":"Bhagvanpura","Latitude":21.5707945,"Longitude":75.1991407,"STATE LGD":23,"DISTRICT LGD":414,"BLOCK LGD":3892,"STATE":"Madhya Pradesh","DISTRICT":"Khargone"},{"BLOCK":"Bhagwanpur","Latitude":25.5564755,"Longitude":86.0012663,"STATE LGD":10,"DISTRICT LGD":191,"BLOCK LGD":1660,"STATE":"Bihar","DISTRICT":"Begusarai"},{"BLOCK":"Bhagwanpur","Latitude":24.9450798,"Longitude":83.590946,"STATE LGD":10,"DISTRICT LGD":191,"BLOCK LGD":1660,"STATE":"Bihar","DISTRICT":"Kaimur (Bhabua)"},{"BLOCK":"Bhamini","Latitude":18.9017748,"Longitude":83.654063,"STATE LGD":28,"DISTRICT LGD":743,"BLOCK LGD":5544,"STATE":"Andhra Pradesh","DISTRICT":"Parvathipuram Manyam"},{"BLOCK":"Bhamragarh","Latitude":19.4143775,"Longitude":80.5838585,"STATE LGD":27,"DISTRICT LGD":475,"BLOCK LGD":4373,"STATE":"Maharashtra","DISTRICT":"Gadhichiroli"},{"BLOCK":"Bhergaon","Latitude":26.6597768,"Longitude":91.7801053,"STATE LGD":18,"DISTRICT LGD":617,"BLOCK LGD":6549,"STATE":"Assam","DISTRICT":"Udalguri"},{"BLOCK":"Bhim","Latitude":25.7417637,"Longitude":74.059653,"STATE LGD":8,"DISTRICT LGD":112,"BLOCK LGD":762,"STATE":"Rajasthan","DISTRICT":"Rajsamand"},{"BLOCK":"Bhiti","Latitude":26.4343191,"Longitude":82.3246489,"STATE LGD":9,"DISTRICT LGD":121,"BLOCK LGD":852,"STATE":"Uttar Pradesh","DISTRICT":"Ambedkar Nagar"},{"BLOCK":"Bhiyawn","Latitude":26.3389469,"Longitude":82.7788653,"STATE LGD":9,"DISTRICT LGD":121,"BLOCK LGD":853,"STATE":"Uttar Pradesh","DISTRICT":"Ambedkar Nagar"},{"BLOCK":"Binpur-1","Latitude":22.5821956,"Longitude":86.9122624,"STATE LGD":19,"DISTRICT LGD":703,"BLOCK LGD":2972,"STATE":"West Bengal","DISTRICT":"Jhargram"},{"BLOCK":"Binpur-2","Latitude":22.455065,"Longitude":86.9562385,"STATE LGD":19,"DISTRICT LGD":703,"BLOCK LGD":2973,"STATE":"West Bengal","DISTRICT":"Jhargram"},{"BLOCK":"Birshing-Jarua","Latitude":26.0193185,"Longitude":89.9916198,"STATE LGD":18,"DISTRICT LGD":285,"BLOCK LGD":2551,"STATE":"Assam","DISTRICT":"Dhubri"},{"BLOCK":"Bisanda","Latitude":25.4028967,"Longitude":80.6130409,"STATE LGD":9,"DISTRICT LGD":128,"BLOCK LGD":936,"STATE":"Uttar Pradesh","DISTRICT":"Banda"},{"BLOCK":"Biswan","Latitude":27.4929869,"Longitude":80.9858464,"STATE LGD":9,"DISTRICT LGD":183,"BLOCK LGD":1552,"STATE":"Uttar Pradesh","DISTRICT":"Sitapur"},{"BLOCK":"Boden","Latitude":20.2767891,"Longitude":82.5672253,"STATE LGD":21,"DISTRICT LGD":368,"BLOCK LGD":3531,"STATE":"Odisha","DISTRICT":"Nuapada"},{"BLOCK":"Bodla","Latitude":22.1641631,"Longitude":81.207647,"STATE LGD":22,"DISTRICT LGD":382,"BLOCK LGD":3665,"STATE":"Chhattisgarh","DISTRICT":"Kabirdham"},{"BLOCK":"Brahmpur","Latitude":25.5997051,"Longitude":84.2898451,"STATE LGD":10,"DISTRICT LGD":194,"BLOCK LGD":1703,"STATE":"Bihar","DISTRICT":"Buxar"},{"BLOCK":"Brahmpur","Latitude":26.5820892,"Longitude":83.582611,"STATE LGD":9,"DISTRICT LGD":148,"BLOCK LGD":1173,"STATE":"Uttar Pradesh","DISTRICT":"Gorakhpur"},{"BLOCK":"Buxwaha","Latitude":24.2502704,"Longitude":79.273653,"STATE LGD":23,"DISTRICT LGD":398,"BLOCK LGD":3784,"STATE":"Madhya Pradesh","DISTRICT":"Chhatarpur"},{"BLOCK":"Car Nicobar","Latitude":9.1873074,"Longitude":92.692278,"STATE LGD":35,"DISTRICT LGD":603,"BLOCK LGD":6499,"STATE":"Andaman And Nicobar Islands","DISTRICT":"Nicobar"},{"BLOCK":"Chahniya","Latitude":25.4085662,"Longitude":83.3045089,"STATE LGD":9,"DISTRICT LGD":135,"BLOCK LGD":1034,"STATE":"Uttar Pradesh","DISTRICT":"Chandauli"},{"BLOCK":"Chakki","Latitude":25.6466294,"Longitude":84.1997334,"STATE LGD":10,"DISTRICT LGD":194,"BLOCK LGD":1705,"STATE":"Bihar","DISTRICT":"Buxar"},{"BLOCK":"Chakpikarong","Latitude":24.3302028,"Longitude":93.9847752,"STATE LGD":14,"DISTRICT LGD":253,"BLOCK LGD":2361,"STATE":"Manipur","DISTRICT":"Chandel"},{"BLOCK":"Chanchal-1","Latitude":25.2874631,"Longitude":87.6154429,"STATE LGD":19,"DISTRICT LGD":316,"BLOCK LGD":2933,"STATE":"West Bengal","DISTRICT":"Maldah"},{"BLOCK":"Chand","Latitude":25.1142755,"Longitude":83.3953982,"STATE LGD":10,"DISTRICT LGD":200,"BLOCK LGD":1791,"STATE":"Bihar","DISTRICT":"Kaimur (Bhabua)"},{"BLOCK":"Chandan","Latitude":24.6176601,"Longitude":86.6481289,"STATE LGD":10,"DISTRICT LGD":190,"BLOCK LGD":1649,"STATE":"Bihar","DISTRICT":"Banka"},{"BLOCK":"Chatra","Latitude":24.5381224,"Longitude":83.2983335,"STATE LGD":9,"DISTRICT LGD":184,"BLOCK LGD":1570,"STATE":"Uttar Pradesh","DISTRICT":"Sonbhadra"},{"BLOCK":"Chhaigaon Makhan","Latitude":21.8313632,"Longitude":76.2124878,"STATE LGD":23,"DISTRICT LGD":405,"BLOCK LGD":3837,"STATE":"Madhya Pradesh","DISTRICT":"Khandwa (East Nimar)"},{"BLOCK":"Chhaohara","Latitude":31.1304455,"Longitude":76.376709,"STATE LGD":2,"DISTRICT LGD":23,"BLOCK LGD":186,"STATE":"Himachal Pradesh","DISTRICT":"Shimla"},{"BLOCK":"Chikhaldara","Latitude":21.4018588,"Longitude":77.323746,"STATE LGD":27,"DISTRICT LGD":468,"BLOCK LGD":4304,"STATE":"Maharashtra","DISTRICT":"Amravati"},{"BLOCK":"Chilkahar","Latitude":25.8234379,"Longitude":83.9578306,"STATE LGD":9,"DISTRICT LGD":126,"BLOCK LGD":912,"STATE":"Uttar Pradesh","DISTRICT":"Ballia"},{"BLOCK":"Chintakomma Dinne","Latitude":14.4279157,"Longitude":78.7409952,"STATE LGD":28,"DISTRICT LGD":504,"BLOCK LGD":4823,"STATE":"Andhra Pradesh","DISTRICT":"Y.S.R."},{"BLOCK":"Chinthong","Latitude":26.1036139,"Longitude":92.7111139,"STATE LGD":18,"DISTRICT LGD":710,"BLOCK LGD":2618,"STATE":"Assam","DISTRICT":"West Karbi Anglong"},{"BLOCK":"Chippagiri","Latitude":15.2275558,"Longitude":77.3089992,"STATE LGD":28,"DISTRICT LGD":511,"BLOCK LGD":5159,"STATE":"Andhra Pradesh","DISTRICT":"Kurnool"},{"BLOCK":"Chitrkonda","Latitude":18.1094911,"Longitude":82.1009587,"STATE LGD":21,"DISTRICT LGD":364,"BLOCK LGD":3483,"STATE":"Odisha","DISTRICT":"Malkangiri"},{"BLOCK":"Chittaguppa","Latitude":17.695872,"Longitude":77.2027274,"STATE LGD":29,"DISTRICT LGD":529,"BLOCK LGD":7430,"STATE":"Karnataka","DISTRICT":"Bidar"},{"BLOCK":"Chopra","Latitude":26.3772867,"Longitude":88.2917331,"STATE LGD":19,"DISTRICT LGD":311,"BLOCK LGD":2878,"STATE":"West Bengal","DISTRICT":"Dinajpur Uttar"},{"BLOCK":"Chouparan","Latitude":24.3778872,"Longitude":85.2494,"STATE LGD":20,"DISTRICT LGD":332,"BLOCK LGD":3166,"STATE":"Jharkhand","DISTRICT":"Hazaribagh"},{"BLOCK":"Chowkham","Latitude":27.8118687,"Longitude":96.0814776,"STATE LGD":12,"DISTRICT LGD":678,"BLOCK LGD":7150,"STATE":"Arunachal Pradesh","DISTRICT":"Namsai"},{"BLOCK":"Chumbong Chakung","Latitude":27.1710854,"Longitude":88.1894981,"STATE LGD":11,"DISTRICT LGD":742,"BLOCK LGD":7140,"STATE":"Sikkim","DISTRICT":"Soreng"},{"BLOCK":"Dabugaon","Latitude":19.4568198,"Longitude":82.3947142,"STATE LGD":21,"DISTRICT LGD":366,"BLOCK LGD":3514,"STATE":"Odisha","DISTRICT":"Nabarangapur"},{"BLOCK":"Dadra Nagar Haveli","Latitude":20.3213467,"Longitude":72.9553126,"STATE LGD":38,"DISTRICT LGD":465,"BLOCK LGD":4276,"STATE":"Dadra & Nagar Haveli And Daman & Diu","DISTRICT":"Dadra And Nagar Haveli"},{"BLOCK":"Dahanu","Latitude":19.9757356,"Longitude":72.7044455,"STATE LGD":27,"DISTRICT LGD":665,"BLOCK LGD":4591,"STATE":"Maharashtra","DISTRICT":"Palghar"},{"BLOCK":"Daman","Latitude":20.3917355,"Longitude":72.8232619,"STATE LGD":38,"DISTRICT LGD":463,"BLOCK LGD":4274,"STATE":"Dadra & Nagar Haveli And Daman & Diu","DISTRICT":"Daman"},{"BLOCK":"Damcherra","Latitude":24.2389618,"Longitude":92.2790729,"STATE LGD":16,"DISTRICT LGD":270,"BLOCK LGD":2415,"STATE":"Tripura","DISTRICT":"North Tripura"},{"BLOCK":"Damkhauda","Latitude":28.680861,"Longitude":79.5315954,"STATE LGD":9,"DISTRICT LGD":130,"BLOCK LGD":965,"STATE":"Uttar Pradesh","DISTRICT":"Bareilly"},{"BLOCK":"Dasapalla","Latitude":20.3338607,"Longitude":84.8350737,"STATE LGD":21,"DISTRICT LGD":367,"BLOCK LGD":3524,"STATE":"Odisha","DISTRICT":"Nayagarh"},{"BLOCK":"Dasda","Latitude":24.0299009,"Longitude":92.1114672,"STATE LGD":16,"DISTRICT LGD":270,"BLOCK LGD":2416,"STATE":"Tripura","DISTRICT":"North Tripura"},{"BLOCK":"Deo","Latitude":24.6582889,"Longitude":84.4278743,"STATE LGD":10,"DISTRICT LGD":189,"BLOCK LGD":1636,"STATE":"Bihar","DISTRICT":"Aurangabad"},{"BLOCK":"Dera Baba Nanak","Latitude":32.0338158,"Longitude":75.0200085,"STATE LGD":3,"DISTRICT LGD":32,"BLOCK LGD":253,"STATE":"Punjab","DISTRICT":"Gurdaspur"},{"BLOCK":"Devikulam","Latitude":10.0527779,"Longitude":77.0983157,"STATE LGD":32,"DISTRICT LGD":556,"BLOCK LGD":5978,"STATE":"Kerala","DISTRICT":"Idukki"},{"BLOCK":"Devipur","Latitude":24.4463228,"Longitude":86.4991302,"STATE LGD":20,"DISTRICT LGD":324,"BLOCK LGD":3083,"STATE":"Jharkhand","DISTRICT":"Deoghar"},{"BLOCK":"Devsar","Latitude":24.2016893,"Longitude":82.2545352,"STATE LGD":23,"DISTRICT LGD":638,"BLOCK LGD":4020,"STATE":"Madhya Pradesh","DISTRICT":"Singrauli"},{"BLOCK":"Dharhara","Latitude":25.2554414,"Longitude":86.3930033,"STATE LGD":10,"DISTRICT LGD":207,"BLOCK LGD":1871,"STATE":"Bihar","DISTRICT":"Munger"},{"BLOCK":"Dharni","Latitude":21.5539095,"Longitude":76.8814015,"STATE LGD":27,"DISTRICT LGD":468,"BLOCK LGD":4307,"STATE":"Maharashtra","DISTRICT":"Amravati"},{"BLOCK":"Dhaurhara","Latitude":27.9883947,"Longitude":81.0477901,"STATE LGD":9,"DISTRICT LGD":159,"BLOCK LGD":1297,"STATE":"Uttar Pradesh","DISTRICT":"Kheri"},{"BLOCK":"Dhilwan","Latitude":31.5129197,"Longitude":75.3191325,"STATE LGD":3,"DISTRICT LGD":35,"BLOCK LGD":287,"STATE":"Punjab","DISTRICT":"Kapurthala"},{"BLOCK":"Dhuri","Latitude":30.3757195,"Longitude":75.8402493,"STATE LGD":3,"DISTRICT LGD":43,"BLOCK LGD":343,"STATE":"Punjab","DISTRICT":"Sangrur"},{"BLOCK":"Diyang Valley","Latitude":25.0952337,"Longitude":92.8781052,"STATE LGD":18,"DISTRICT LGD":299,"BLOCK LGD":2688,"STATE":"Assam","DISTRICT":"Dima Hasao"},{"BLOCK":"Diyungbra","Latitude":25.0952337,"Longitude":92.8781052,"STATE LGD":18,"DISTRICT LGD":299,"BLOCK LGD":2689,"STATE":"Assam","DISTRICT":"Dima Hasao"},{"BLOCK":"Duggada","Latitude":29.8064325,"Longitude":78.6041896,"STATE LGD":5,"DISTRICT LGD":52,"BLOCK LGD":400,"STATE":"Uttarakhand","DISTRICT":"Pauri Garhwal"},{"BLOCK":"Dumri","Latitude":23.1656333,"Longitude":84.132244,"STATE LGD":20,"DISTRICT LGD":331,"BLOCK LGD":3155,"STATE":"Jharkhand","DISTRICT":"Gumla"},{"BLOCK":"Durgukondal","Latitude":20.2854449,"Longitude":80.9178278,"STATE LGD":22,"DISTRICT LGD":381,"BLOCK LGD":3661,"STATE":"Chhattisgarh","DISTRICT":"Kanker"},{"BLOCK":"Fatehganj (West)","Latitude":28.4650906,"Longitude":79.2955198,"STATE LGD":9,"DISTRICT LGD":130,"BLOCK LGD":967,"STATE":"Uttar Pradesh","DISTRICT":"Bareilly"},{"BLOCK":"Fatehpur","Latitude":24.8096632,"Longitude":84.9890189,"STATE LGD":10,"DISTRICT LGD":196,"BLOCK LGD":1740,"STATE":"Bihar","DISTRICT":"Gaya"},{"BLOCK":"Fatehpur","Latitude":24.1092496,"Longitude":86.9760987,"STATE LGD":20,"DISTRICT LGD":333,"BLOCK LGD":6653,"STATE":"Jharkhand","DISTRICT":"Jamtara"},{"BLOCK":"Fathegarh","Latitude":26.7300453,"Longitude":71.5799017,"STATE LGD":8,"DISTRICT LGD":103,"BLOCK LGD":7450,"STATE":"Rajasthan","DISTRICT":"Jaisalmer"},{"BLOCK":"Fekamari","Latitude":25.6950243,"Longitude":89.8862396,"STATE LGD":18,"DISTRICT LGD":707,"BLOCK LGD":2554,"STATE":"Assam","DISTRICT":"SS Mankachar"},{"BLOCK":"Gadarpur","Latitude":29.0402677,"Longitude":79.2301854,"STATE LGD":5,"DISTRICT LGD":56,"BLOCK LGD":435,"STATE":"Uttarakhand","DISTRICT":"Udam Singh Nagar"},{"BLOCK":"Gamharia","Latitude":22.8027968,"Longitude":86.0625061,"STATE LGD":20,"DISTRICT LGD":341,"BLOCK LGD":3247,"STATE":"Jharkhand","DISTRICT":"Saraikela Kharsawan"},{"BLOCK":"Ganganagar","Latitude":23.7739631,"Longitude":91.7825601,"STATE LGD":16,"DISTRICT LGD":269,"BLOCK LGD":6781,"STATE":"Tripura","DISTRICT":"Dhalai"},{"BLOCK":"Gangapur City","Latitude":26.4819754,"Longitude":76.6872609,"STATE LGD":8,"DISTRICT LGD":113,"BLOCK LGD":770,"STATE":"Rajasthan","DISTRICT":"S. Madhopur"},{"BLOCK":"Gangaram","Latitude":17.824918,"Longitude":80.1912688,"STATE LGD":36,"DISTRICT LGD":688,"BLOCK LGD":7216,"STATE":"Telangana","DISTRICT":"Mahabubabad"},{"BLOCK":"Gangavaram","Latitude":17.2519278,"Longitude":80.7660232,"STATE LGD":28,"DISTRICT LGD":745,"BLOCK LGD":4876,"STATE":"Andhra Pradesh","DISTRICT":"Alluri Sitharama Raju"},{"BLOCK":"Gangiri","Latitude":27.8497104,"Longitude":78.4511375,"STATE LGD":9,"DISTRICT LGD":119,"BLOCK LGD":823,"STATE":"Uttar Pradesh","DISTRICT":"Aligarh"},{"BLOCK":"Ganj Dundwara","Latitude":27.7346626,"Longitude":78.9165559,"STATE LGD":9,"DISTRICT LGD":633,"BLOCK LGD":1066,"STATE":"Uttar Pradesh","DISTRICT":"Kasganj"},{"BLOCK":"Garbada","Latitude":22.6854888,"Longitude":74.3085836,"STATE LGD":24,"DISTRICT LGD":445,"BLOCK LGD":4115,"STATE":"Gujarat","DISTRICT":"Dohad"},{"BLOCK":"Gariyaband","Latitude":20.6348091,"Longitude":82.0511976,"STATE LGD":22,"DISTRICT LGD":645,"BLOCK LGD":3702,"STATE":"Chhattisgarh","DISTRICT":"Gariyaband"},{"BLOCK":"Gaurella-2","Latitude":22.7536554,"Longitude":81.8816796,"STATE LGD":22,"DISTRICT LGD":734,"BLOCK LGD":3606,"STATE":"Chhattisgarh","DISTRICT":"Gaurella-Pendra-Marwahi"},{"BLOCK":"Gauri Bazar","Latitude":26.5950353,"Longitude":83.6595169,"STATE LGD":9,"DISTRICT LGD":137,"BLOCK LGD":1056,"STATE":"Uttar Pradesh","DISTRICT":"Deoria"},{"BLOCK":"Ghattu","Latitude":16.1385852,"Longitude":77.5577903,"STATE LGD":36,"DISTRICT LGD":695,"BLOCK LGD":5224,"STATE":"Telangana","DISTRICT":"Jogulamba Gadwal"},{"BLOCK":"Ghoghamba","Latitude":22.5714962,"Longitude":73.6326241,"STATE LGD":24,"DISTRICT LGD":454,"BLOCK LGD":4184,"STATE":"Gujarat","DISTRICT":"Panch Mahals"},{"BLOCK":"Goalpokher-1","Latitude":26.0884171,"Longitude":88.126279,"STATE LGD":19,"DISTRICT LGD":311,"BLOCK LGD":2880,"STATE":"West Bengal","DISTRICT":"Dinajpur Uttar"},{"BLOCK":"Goalpokher-2","Latitude":26.0579953,"Longitude":87.9538217,"STATE LGD":19,"DISTRICT LGD":311,"BLOCK LGD":2879,"STATE":"West Bengal","DISTRICT":"Dinajpur Uttar"},{"BLOCK":"Gohad","Latitude":26.4426213,"Longitude":78.4143069,"STATE LGD":23,"DISTRICT LGD":395,"BLOCK LGD":3773,"STATE":"Madhya Pradesh","DISTRICT":"Bhind"},{"BLOCK":"Gomia","Latitude":23.8024578,"Longitude":85.7861412,"STATE LGD":20,"DISTRICT LGD":322,"BLOCK LGD":3067,"STATE":"Jharkhand","DISTRICT":"Bokaro"},{"BLOCK":"Gopiballavpur-1","Latitude":22.2065143,"Longitude":86.8766245,"STATE LGD":19,"DISTRICT LGD":703,"BLOCK LGD":2986,"STATE":"West Bengal","DISTRICT":"Jhargram"},{"BLOCK":"Gopiballavpur-2","Latitude":22.2065143,"Longitude":86.8766245,"STATE LGD":19,"DISTRICT LGD":703,"BLOCK LGD":2985,"STATE":"West Bengal","DISTRICT":"Jhargram"},{"BLOCK":"Govindpur","Latitude":23.8324682,"Longitude":86.4992675,"STATE LGD":20,"DISTRICT LGD":325,"BLOCK LGD":3093,"STATE":"Jharkhand","DISTRICT":"Dhanbad"},{"BLOCK":"Gudri","Latitude":22.6519121,"Longitude":85.0795389,"STATE LGD":20,"DISTRICT LGD":343,"BLOCK LGD":6610,"STATE":"Jharkhand","DISTRICT":"West Singhbhum"},{"BLOCK":"Gudvella","Latitude":20.4128428,"Longitude":83.5673087,"STATE LGD":21,"DISTRICT LGD":345,"BLOCK LGD":3289,"STATE":"Odisha","DISTRICT":"Balangir"},{"BLOCK":"Gumma","Latitude":18.9799792,"Longitude":84.0083741,"STATE LGD":21,"DISTRICT LGD":353,"BLOCK LGD":3358,"STATE":"Odisha","DISTRICT":"Gajapati"},{"BLOCK":"Gundala","Latitude":18.9799792,"Longitude":84.0083741,"STATE LGD":36,"DISTRICT LGD":690,"BLOCK LGD":5067,"STATE":"Telangana","DISTRICT":"Bhadradri-Kothagudem"},{"BLOCK":"Gunnaur","Latitude":28.2386485,"Longitude":78.4284138,"STATE LGD":9,"DISTRICT LGD":659,"BLOCK LGD":1004,"STATE":"Uttar Pradesh","DISTRICT":"Sambhal"},{"BLOCK":"Habibpur","Latitude":25.0081324,"Longitude":88.2698354,"STATE LGD":19,"DISTRICT LGD":316,"BLOCK LGD":2937,"STATE":"West Bengal","DISTRICT":"Maldah"},{"BLOCK":"Hallia","Latitude":24.8288157,"Longitude":82.3174667,"STATE LGD":9,"DISTRICT LGD":170,"BLOCK LGD":1401,"STATE":"Uttar Pradesh","DISTRICT":"Mirzapur"},{"BLOCK":"Hanumana","Latitude":24.7772464,"Longitude":82.0810031,"STATE LGD":23,"DISTRICT LGD":424,"BLOCK LGD":3955,"STATE":"Madhya Pradesh","DISTRICT":"Rewa"},{"BLOCK":"Harichandanpur","Latitude":21.3405084,"Longitude":85.7863247,"STATE LGD":21,"DISTRICT LGD":361,"BLOCK LGD":3448,"STATE":"Odisha","DISTRICT":"Kendujhar"},{"BLOCK":"Hariharganj","Latitude":24.545483,"Longitude":84.2687201,"STATE LGD":20,"DISTRICT LGD":338,"BLOCK LGD":3209,"STATE":"Jharkhand","DISTRICT":"Palamu"},{"BLOCK":"Harishchandrapur-2","Latitude":25.4272689,"Longitude":87.8953595,"STATE LGD":19,"DISTRICT LGD":316,"BLOCK LGD":2939,"STATE":"West Bengal","DISTRICT":"Maldah"},{"BLOCK":"Harraiya","Latitude":26.793706,"Longitude":82.4611794,"STATE LGD":9,"DISTRICT LGD":131,"BLOCK LGD":979,"STATE":"Uttar Pradesh","DISTRICT":"Basti"},{"BLOCK":"Harshe Chhina","Latitude":31.7440948,"Longitude":74.7552654,"STATE LGD":3,"DISTRICT LGD":27,"BLOCK LGD":215,"STATE":"Punjab","DISTRICT":"Amritsar"},{"BLOCK":"Hasanpur","Latitude":25.7443551,"Longitude":86.1847911,"STATE LGD":10,"DISTRICT LGD":217,"BLOCK LGD":2042,"STATE":"Bihar","DISTRICT":"Samastipur"},{"BLOCK":"Hathgaon","Latitude":25.8680871,"Longitude":81.1173083,"STATE LGD":9,"DISTRICT LGD":142,"BLOCK LGD":1111,"STATE":"Uttar Pradesh","DISTRICT":"Fatehpur"},{"BLOCK":"Hathin","Latitude":28.0321213,"Longitude":77.2257704,"STATE LGD":6,"DISTRICT LGD":619,"BLOCK LGD":466,"STATE":"Haryana","DISTRICT":"Palwal"},{"BLOCK":"Hemtabad","Latitude":25.6748431,"Longitude":88.211121,"STATE LGD":19,"DISTRICT LGD":311,"BLOCK LGD":2881,"STATE":"West Bengal","DISTRICT":"Dinajpur Uttar"},{"BLOCK":"Hingoli","Latitude":19.7225679,"Longitude":77.1116984,"STATE LGD":27,"DISTRICT LGD":477,"BLOCK LGD":4393,"STATE":"Maharashtra","DISTRICT":"Hingoli"},{"BLOCK":"Holagunda","Latitude":15.488922,"Longitude":77.0401006,"STATE LGD":28,"DISTRICT LGD":511,"BLOCK LGD":5168,"STATE":"Andhra Pradesh","DISTRICT":"Kurnool"},{"BLOCK":"Humnabad","Latitude":17.7703871,"Longitude":77.1113846,"STATE LGD":29,"DISTRICT LGD":529,"BLOCK LGD":5792,"STATE":"Karnataka","DISTRICT":"Bidar"},{"BLOCK":"Hura","Latitude":23.3028631,"Longitude":86.6466808,"STATE LGD":19,"DISTRICT LGD":321,"BLOCK LGD":3049,"STATE":"West Bengal","DISTRICT":"Purulia"},{"BLOCK":"Huzoorpur","Latitude":27.3481288,"Longitude":81.6586352,"STATE LGD":9,"DISTRICT LGD":125,"BLOCK LGD":896,"STATE":"Uttar Pradesh","DISTRICT":"Bahraich"},{"BLOCK":"Ibrahimpatnam","Latitude":16.5934139,"Longitude":80.5133277,"STATE LGD":28,"DISTRICT LGD":749,"BLOCK LGD":5114,"STATE":"Andhra Pradesh","DISTRICT":"NTR"},{"BLOCK":"Ichegoza","Latitude":33.9476024,"Longitude":74.8085538,"STATE LGD":1,"DISTRICT LGD":11,"BLOCK LGD":7088,"STATE":"Jammu & Kashmir","DISTRICT":"Pulwama"},{"BLOCK":"Imamganj","Latitude":24.4552196,"Longitude":84.5712838,"STATE LGD":10,"DISTRICT LGD":196,"BLOCK LGD":1744,"STATE":"Bihar","DISTRICT":"Gaya"},{"BLOCK":"Indpur","Latitude":23.1649461,"Longitude":86.9323718,"STATE LGD":19,"DISTRICT LGD":305,"BLOCK LGD":2780,"STATE":"West Bengal","DISTRICT":"Bankura"},{"BLOCK":"Islampur","Latitude":26.2593749,"Longitude":88.1696266,"STATE LGD":19,"DISTRICT LGD":311,"BLOCK LGD":2882,"STATE":"West Bengal","DISTRICT":"Dinajpur Uttar"},{"BLOCK":"Itahar","Latitude":25.448609,"Longitude":88.1629228,"STATE LGD":19,"DISTRICT LGD":311,"BLOCK LGD":2883,"STATE":"West Bengal","DISTRICT":"Dinajpur Uttar"},{"BLOCK":"Jagdishpur","Latitude":25.1466255,"Longitude":86.9710124,"STATE LGD":10,"DISTRICT LGD":192,"BLOCK LGD":1678,"STATE":"Bihar","DISTRICT":"Bhagalpur"},{"BLOCK":"Jagdishpur","Latitude":26.7479545,"Longitude":80.5390901,"STATE LGD":9,"DISTRICT LGD":640,"BLOCK LGD":1587,"STATE":"Uttar Pradesh","DISTRICT":"Amethi"},{"BLOCK":"Jainagar","Latitude":24.3709815,"Longitude":85.6241365,"STATE LGD":20,"DISTRICT LGD":334,"BLOCK LGD":3182,"STATE":"Jharkhand","DISTRICT":"Koderma"},{"BLOCK":"Jaithra","Latitude":27.5180951,"Longitude":78.96484,"STATE LGD":9,"DISTRICT LGD":138,"BLOCK LGD":1067,"STATE":"Uttar Pradesh","DISTRICT":"Etah"},{"BLOCK":"Jalaun","Latitude":26.1416359,"Longitude":79.2892086,"STATE LGD":9,"DISTRICT LGD":151,"BLOCK LGD":1215,"STATE":"Uttar Pradesh","DISTRICT":"Jalaun"},{"BLOCK":"Jamalpur","Latitude":25.3118022,"Longitude":86.4714142,"STATE LGD":10,"DISTRICT LGD":207,"BLOCK LGD":1872,"STATE":"Bihar","DISTRICT":"Munger"},{"BLOCK":"Jammalamadugu","Latitude":14.8481467,"Longitude":78.3411442,"STATE LGD":28,"DISTRICT LGD":504,"BLOCK LGD":4828,"STATE":"Andhra Pradesh","DISTRICT":"Y.S.R."},{"BLOCK":"Jamo","Latitude":26.316472,"Longitude":81.5915928,"STATE LGD":9,"DISTRICT LGD":640,"BLOCK LGD":1589,"STATE":"Uttar Pradesh","DISTRICT":"Amethi"},{"BLOCK":"Jamua","Latitude":24.3682125,"Longitude":86.1349421,"STATE LGD":20,"DISTRICT LGD":329,"BLOCK LGD":3140,"STATE":"Jharkhand","DISTRICT":"Giridih"},{"BLOCK":"Jamunaha","Latitude":27.8882644,"Longitude":81.7567563,"STATE LGD":9,"DISTRICT LGD":181,"BLOCK LGD":1534,"STATE":"Uttar Pradesh","DISTRICT":"Shravasti"},{"BLOCK":"Jarmundi","Latitude":24.3966438,"Longitude":87.0399141,"STATE LGD":20,"DISTRICT LGD":326,"BLOCK LGD":3101,"STATE":"Jharkhand","DISTRICT":"Dumka"},{"BLOCK":"Jatinga Valley","Latitude":25.3524006,"Longitude":92.3376725,"STATE LGD":18,"DISTRICT LGD":299,"BLOCK LGD":2691,"STATE":"Assam","DISTRICT":"Dima Hasao"},{"BLOCK":"Jawa","Latitude":24.9633146,"Longitude":81.4875859,"STATE LGD":23,"DISTRICT LGD":424,"BLOCK LGD":3956,"STATE":"Madhya Pradesh","DISTRICT":"Rewa"},{"BLOCK":"Jawahar","Latitude":19.9077595,"Longitude":73.2252052,"STATE LGD":27,"DISTRICT LGD":665,"BLOCK LGD":4592,"STATE":"Maharashtra","DISTRICT":"Palghar"},{"BLOCK":"Jawathu Hills","Latitude":12.5999841,"Longitude":78.8843037,"STATE LGD":33,"DISTRICT LGD":593,"BLOCK LGD":6408,"STATE":"Tamil Nadu","DISTRICT":"Thiruvannamalai"},{"BLOCK":"Jayal","Latitude":27.2217979,"Longitude":74.1671553,"STATE LGD":8,"DISTRICT LGD":110,"BLOCK LGD":742,"STATE":"Rajasthan","DISTRICT":"Nagaur"},{"BLOCK":"Jiwati","Latitude":19.6340749,"Longitude":79.0660102,"STATE LGD":27,"DISTRICT LGD":473,"BLOCK LGD":4358,"STATE":"Maharashtra","DISTRICT":"Chandrapur"},{"BLOCK":"Joshipur","Latitude":21.969852,"Longitude":86.0698985,"STATE LGD":21,"DISTRICT LGD":365,"BLOCK LGD":3496,"STATE":"Odisha","DISTRICT":"Mayurbhanj"},{"BLOCK":"Jothari","Latitude":25.0771967,"Longitude":72.3189559,"STATE LGD":8,"DISTRICT LGD":99,"BLOCK LGD":6826,"STATE":"Rajasthan","DISTRICT":"Dungarpur"},{"BLOCK":"K.V.Kuppam","Latitude":12.8831257,"Longitude":79.0663072,"STATE LGD":33,"DISTRICT LGD":595,"BLOCK LGD":6439,"STATE":"Tamil Nadu","DISTRICT":"Vellore"},{"BLOCK":"Kabrai","Latitude":25.4051713,"Longitude":79.9818632,"STATE LGD":9,"DISTRICT LGD":165,"BLOCK LGD":1358,"STATE":"Uttar Pradesh","DISTRICT":"Mahoba"},{"BLOCK":"Kalagi","Latitude":17.3557665,"Longitude":77.1425414,"STATE LGD":29,"DISTRICT LGD":538,"BLOCK LGD":7406,"STATE":"Karnataka","DISTRICT":"Kalburgi"},{"BLOCK":"Kalanaur","Latitude":32.0115324,"Longitude":75.1378475,"STATE LGD":3,"DISTRICT LGD":32,"BLOCK LGD":261,"STATE":"Punjab","DISTRICT":"Gurdaspur"},{"BLOCK":"Kalpetta","Latitude":11.6161657,"Longitude":76.0446154,"STATE LGD":32,"DISTRICT LGD":567,"BLOCK LGD":6098,"STATE":"Kerala","DISTRICT":"Wayanad"},{"BLOCK":"Kalvarayan Hills","Latitude":11.7042864,"Longitude":78.7254523,"STATE LGD":33,"DISTRICT LGD":729,"BLOCK LGD":6456,"STATE":"Tamil Nadu","DISTRICT":"Kallakurichi"},{"BLOCK":"Kalyanpur","Latitude":26.4393089,"Longitude":84.9069439,"STATE LGD":10,"DISTRICT LGD":213,"BLOCK LGD":1979,"STATE":"Bihar","DISTRICT":"Purbi Champaran"},{"BLOCK":"Kamalanagara","Latitude":18.0573525,"Longitude":77.1785094,"STATE LGD":29,"DISTRICT LGD":529,"BLOCK LGD":7432,"STATE":"Karnataka","DISTRICT":"Bidar"},{"BLOCK":"Kampli","Latitude":15.405258,"Longitude":76.5928601,"STATE LGD":29,"DISTRICT LGD":528,"BLOCK LGD":7375,"STATE":"Karnataka","DISTRICT":"Ballari"},{"BLOCK":"Kankada Had","Latitude":21.0864688,"Longitude":85.5530453,"STATE LGD":21,"DISTRICT LGD":352,"BLOCK LGD":3354,"STATE":"Odisha","DISTRICT":"Dhenkanal"},{"BLOCK":"Kannaigudem","Latitude":18.1737372,"Longitude":80.13778,"STATE LGD":36,"DISTRICT LGD":720,"BLOCK LGD":7253,"STATE":"Telangana","DISTRICT":"Mulugu"},{"BLOCK":"Kapkote","Latitude":29.9456346,"Longitude":79.8746392,"STATE LGD":5,"DISTRICT LGD":46,"BLOCK LGD":365,"STATE":"Uttarakhand","DISTRICT":"Bageshwar"},{"BLOCK":"Karahal","Latitude":25.4824868,"Longitude":76.9988601,"STATE LGD":23,"DISTRICT LGD":431,"BLOCK LGD":4008,"STATE":"Madhya Pradesh","DISTRICT":"Sheopur"},{"BLOCK":"Karanja","Latitude":21.1627212,"Longitude":78.4002398,"STATE LGD":27,"DISTRICT LGD":498,"BLOCK LGD":4608,"STATE":"Maharashtra","DISTRICT":"Wardha"},{"BLOCK":"Karanjia","Latitude":22.7105691,"Longitude":81.6286622,"STATE LGD":23,"DISTRICT LGD":404,"BLOCK LGD":3832,"STATE":"Madhya Pradesh","DISTRICT":"Dindori"},{"BLOCK":"Karmatanr Vidyasagar","Latitude":24.0885108,"Longitude":86.6542631,"STATE LGD":20,"DISTRICT LGD":333,"BLOCK LGD":6654,"STATE":"Jharkhand","DISTRICT":"Jamtara"},{"BLOCK":"Karown","Latitude":24.1251864,"Longitude":86.7414271,"STATE LGD":20,"DISTRICT LGD":324,"BLOCK LGD":3084,"STATE":"Jharkhand","DISTRICT":"Deoghar"},{"BLOCK":"Karra","Latitude":23.1268844,"Longitude":85.1219102,"STATE LGD":20,"DISTRICT LGD":606,"BLOCK LGD":3225,"STATE":"Jharkhand","DISTRICT":"Khunti"},{"BLOCK":"Karsha","Latitude":33.5314367,"Longitude":76.9009817,"STATE LGD":37,"DISTRICT LGD":6,"BLOCK LGD":7043,"STATE":"Ladakh","DISTRICT":"Kargil"},{"BLOCK":"Kashichak","Latitude":25.071217,"Longitude":85.7134759,"STATE LGD":10,"DISTRICT LGD":210,"BLOCK LGD":1917,"STATE":"Bihar","DISTRICT":"Nawada"},{"BLOCK":"Kashipur","Latitude":23.4330934,"Longitude":86.6610688,"STATE LGD":19,"DISTRICT LGD":321,"BLOCK LGD":3053,"STATE":"West Bengal","DISTRICT":"Purulia"},{"BLOCK":"Katkamdag","Latitude":23.9778528,"Longitude":85.2661903,"STATE LGD":20,"DISTRICT LGD":332,"BLOCK LGD":6708,"STATE":"Jharkhand","DISTRICT":"Hazaribagh"},{"BLOCK":"Katoria","Latitude":24.7461619,"Longitude":86.7162485,"STATE LGD":10,"DISTRICT LGD":190,"BLOCK LGD":1652,"STATE":"Bihar","DISTRICT":"Banka"},{"BLOCK":"Kattiwada","Latitude":22.483352,"Longitude":74.1397002,"STATE LGD":23,"DISTRICT LGD":639,"BLOCK LGD":3877,"STATE":"Madhya Pradesh","DISTRICT":"Alirajpur"},{"BLOCK":"Kaushambi","Latitude":25.3590536,"Longitude":81.3944434,"STATE LGD":9,"DISTRICT LGD":158,"BLOCK LGD":1288,"STATE":"Uttar Pradesh","DISTRICT":"Kaushambi"},{"BLOCK":"Kawant","Latitude":22.0928123,"Longitude":74.0498484,"STATE LGD":24,"DISTRICT LGD":668,"BLOCK LGD":4261,"STATE":"Gujarat","DISTRICT":"Chhotaudepur"},{"BLOCK":"Keran","Latitude":34.6600116,"Longitude":73.9391635,"STATE LGD":1,"DISTRICT LGD":8,"BLOCK LGD":6992,"STATE":"Jammu & Kashmir","DISTRICT":"Kupwara"},{"BLOCK":"Kesaria","Latitude":26.3528723,"Longitude":84.8605978,"STATE LGD":10,"DISTRICT LGD":213,"BLOCK LGD":1980,"STATE":"Bihar","DISTRICT":"Purbi Champaran"},{"BLOCK":"Keshiary","Latitude":22.1174073,"Longitude":87.2151371,"STATE LGD":19,"DISTRICT LGD":318,"BLOCK LGD":2990,"STATE":"West Bengal","DISTRICT":"Medinipur West"},{"BLOCK":"Keshoraipatan","Latitude":25.2956732,"Longitude":75.9286161,"STATE LGD":8,"DISTRICT LGD":94,"BLOCK LGD":637,"STATE":"Rajasthan","DISTRICT":"Bundi"},{"BLOCK":"Khaira","Latitude":24.8746317,"Longitude":86.1923825,"STATE LGD":10,"DISTRICT LGD":198,"BLOCK LGD":1776,"STATE":"Bihar","DISTRICT":"Jamui"},{"BLOCK":"Khairaput","Latitude":18.4859381,"Longitude":82.2338784,"STATE LGD":21,"DISTRICT LGD":364,"BLOCK LGD":3481,"STATE":"Odisha","DISTRICT":"Malkangiri"},{"BLOCK":"Khanpur","Latitude":25.8673577,"Longitude":85.9165351,"STATE LGD":10,"DISTRICT LGD":217,"BLOCK LGD":2044,"STATE":"Bihar","DISTRICT":"Samastipur"},{"BLOCK":"Khanpur","Latitude":25.8673577,"Longitude":85.9165351,"STATE LGD":8,"DISTRICT LGD":105,"BLOCK LGD":710,"STATE":"Rajasthan","DISTRICT":"Jhalawar"},{"BLOCK":"Khari","Latitude":33.3832658,"Longitude":75.1516342,"STATE LGD":1,"DISTRICT LGD":621,"BLOCK LGD":6952,"STATE":"Jammu & Kashmir","DISTRICT":"Ramban"},{"BLOCK":"Khatra-1","Latitude":22.9517865,"Longitude":86.633723,"STATE LGD":19,"DISTRICT LGD":305,"BLOCK LGD":2783,"STATE":"West Bengal","DISTRICT":"Bankura"},{"BLOCK":"Kherwara","Latitude":23.9906278,"Longitude":73.5890153,"STATE LGD":8,"DISTRICT LGD":117,"BLOCK LGD":798,"STATE":"Rajasthan","DISTRICT":"Udaipur"},{"BLOCK":"Khesraha","Latitude":27.0715495,"Longitude":82.9574351,"STATE LGD":9,"DISTRICT LGD":182,"BLOCK LGD":1543,"STATE":"Uttar Pradesh","DISTRICT":"Siddharth Nagar"},{"BLOCK":"Khonsa","Latitude":25.8693604,"Longitude":94.7828937,"STATE LGD":13,"DISTRICT LGD":614,"BLOCK LGD":6758,"STATE":"Nagaland","DISTRICT":"Kiphire"},{"BLOCK":"Khoyrasol","Latitude":23.7853833,"Longitude":87.2562718,"STATE LGD":19,"DISTRICT LGD":307,"BLOCK LGD":2830,"STATE":"West Bengal","DISTRICT":"Birbhum"},{"BLOCK":"Khwas","Latitude":33.2952669,"Longitude":74.548357,"STATE LGD":1,"DISTRICT LGD":12,"BLOCK LGD":6954,"STATE":"Jammu & Kashmir","DISTRICT":"Rajouri"},{"BLOCK":"Kinwat","Latitude":19.6214331,"Longitude":78.179054,"STATE LGD":27,"DISTRICT LGD":485,"BLOCK LGD":4465,"STATE":"Maharashtra","DISTRICT":"Nanded"},{"BLOCK":"Kishanganj","Latitude":25.1203084,"Longitude":76.6227127,"STATE LGD":8,"DISTRICT LGD":89,"BLOCK LGD":601,"STATE":"Rajasthan","DISTRICT":"Baran"},{"BLOCK":"Kisko","Latitude":23.5148068,"Longitude":84.6606446,"STATE LGD":20,"DISTRICT LGD":336,"BLOCK LGD":3194,"STATE":"Jharkhand","DISTRICT":"Lohardaga"},{"BLOCK":"Kodur","Latitude":16.1101179,"Longitude":77.9037859,"STATE LGD":28,"DISTRICT LGD":753,"BLOCK LGD":4832,"STATE":"Andhra Pradesh","DISTRICT":"Annamayya"},{"BLOCK":"Koilebeda","Latitude":19.9627436,"Longitude":80.9808409,"STATE LGD":22,"DISTRICT LGD":381,"BLOCK LGD":3663,"STATE":"Chhattisgarh","DISTRICT":"Kanker"},{"BLOCK":"Kolaras","Latitude":25.2212284,"Longitude":77.6005983,"STATE LGD":23,"DISTRICT LGD":432,"BLOCK LGD":4014,"STATE":"Madhya Pradesh","DISTRICT":"Shivpuri"},{"BLOCK":"Kolayat","Latitude":27.8376193,"Longitude":72.9341555,"STATE LGD":8,"DISTRICT LGD":93,"BLOCK LGD":632,"STATE":"Rajasthan","DISTRICT":"Bikaner"},{"BLOCK":"Kollengode","Latitude":10.6136631,"Longitude":76.6852093,"STATE LGD":32,"DISTRICT LGD":563,"BLOCK LGD":6050,"STATE":"Kerala","DISTRICT":"Palakkad"},{"BLOCK":"Komna","Latitude":20.5030235,"Longitude":82.6671838,"STATE LGD":21,"DISTRICT LGD":368,"BLOCK LGD":3533,"STATE":"Odisha","DISTRICT":"Nuapada"},{"BLOCK":"Konch","Latitude":24.9277338,"Longitude":84.7610409,"STATE LGD":10,"DISTRICT LGD":196,"BLOCK LGD":1746,"STATE":"Bihar","DISTRICT":"Gaya"},{"BLOCK":"Konta","Latitude":17.8092681,"Longitude":81.372779,"STATE LGD":22,"DISTRICT LGD":642,"BLOCK LGD":3621,"STATE":"Chhattisgarh","DISTRICT":"Sukma"},{"BLOCK":"Koraon","Latitude":24.9978248,"Longitude":82.0578821,"STATE LGD":9,"DISTRICT LGD":120,"BLOCK LGD":840,"STATE":"Uttar Pradesh","DISTRICT":"Prayagraj"},{"BLOCK":"Korba","Latitude":22.3345485,"Longitude":82.5820298,"STATE LGD":22,"DISTRICT LGD":383,"BLOCK LGD":3671,"STATE":"Chhattisgarh","DISTRICT":"Korba"},{"BLOCK":"Kothagiri","Latitude":11.4217873,"Longitude":76.8514277,"STATE LGD":33,"DISTRICT LGD":587,"BLOCK LGD":6336,"STATE":"Tamil Nadu","DISTRICT":"The Nilgiris"},{"BLOCK":"Kotri","Latitude":25.4016055,"Longitude":74.8764607,"STATE LGD":8,"DISTRICT LGD":92,"BLOCK LGD":624,"STATE":"Rajasthan","DISTRICT":"Bhilwara"},{"BLOCK":"Kotwali","Latitude":29.3765486,"Longitude":78.3659354,"STATE LGD":9,"DISTRICT LGD":132,"BLOCK LGD":994,"STATE":"Uttar Pradesh","DISTRICT":"Bijanaur"},{"BLOCK":"Kudaraha","Latitude":26.6065931,"Longitude":82.7844146,"STATE LGD":9,"DISTRICT LGD":131,"BLOCK LGD":981,"STATE":"Uttar Pradesh","DISTRICT":"Basti"},{"BLOCK":"Kudra","Latitude":25.0461233,"Longitude":83.7832179,"STATE LGD":10,"DISTRICT LGD":200,"BLOCK LGD":1793,"STATE":"Bihar","DISTRICT":"Kaimur (Bhabua)"},{"BLOCK":"Kukarmunda","Latitude":21.5462994,"Longitude":74.1209149,"STATE LGD":24,"DISTRICT LGD":641,"BLOCK LGD":7130,"STATE":"Gujarat","DISTRICT":"Tapi"},{"BLOCK":"Kukru","Latitude":23.114458,"Longitude":85.9634553,"STATE LGD":20,"DISTRICT LGD":341,"BLOCK LGD":6652,"STATE":"Jharkhand","DISTRICT":"Saraikela Kharsawan"},{"BLOCK":"Kumarganj","Latitude":25.4237586,"Longitude":88.7077328,"STATE LGD":19,"DISTRICT LGD":310,"BLOCK LGD":2875,"STATE":"West Bengal","DISTRICT":"Dinajpur Dakshin"},{"BLOCK":"Kupvi","Latitude":30.8312198,"Longitude":77.568098,"STATE LGD":2,"DISTRICT LGD":23,"BLOCK LGD":7348,"STATE":"Himachal Pradesh","DISTRICT":"Shimla"},{"BLOCK":"Kurabalakota","Latitude":13.8138893,"Longitude":78.5182819,"STATE LGD":28,"DISTRICT LGD":753,"BLOCK LGD":4769,"STATE":"Andhra Pradesh","DISTRICT":"Annamayya"},{"BLOCK":"Kursela","Latitude":25.4506599,"Longitude":87.2457955,"STATE LGD":10,"DISTRICT LGD":201,"BLOCK LGD":1809,"STATE":"Bihar","DISTRICT":"Katihar"},{"BLOCK":"Kutumba","Latitude":24.6149748,"Longitude":84.2179201,"STATE LGD":10,"DISTRICT LGD":189,"BLOCK LGD":1639,"STATE":"Bihar","DISTRICT":"Aurangabad"},{"BLOCK":"Kuwakonda","Latitude":18.7269626,"Longitude":81.412998,"STATE LGD":22,"DISTRICT LGD":376,"BLOCK LGD":3622,"STATE":"Chhattisgarh","DISTRICT":"Dantewada"},{"BLOCK":"Lakhanpur","Latitude":22.9788793,"Longitude":83.0359116,"STATE LGD":22,"DISTRICT LGD":389,"BLOCK LGD":3722,"STATE":"Chhattisgarh","DISTRICT":"Surguja"},{"BLOCK":"Lakhipur","Latitude":24.7967186,"Longitude":92.9816038,"STATE LGD":18,"DISTRICT LGD":282,"BLOCK LGD":2514,"STATE":"Assam","DISTRICT":"Cachar"},{"BLOCK":"Lakhipur","Latitude":26.035701,"Longitude":90.2932847,"STATE LGD":18,"DISTRICT LGD":287,"BLOCK LGD":2575,"STATE":"Assam","DISTRICT":"Goalpara"},{"BLOCK":"Lakhpat","Latitude":23.8138231,"Longitude":68.719935,"STATE LGD":24,"DISTRICT LGD":449,"BLOCK LGD":4151,"STATE":"Gujarat","DISTRICT":"Kachchh"},{"BLOCK":"Lakkireddipalle","Latitude":14.1424558,"Longitude":78.4133652,"STATE LGD":28,"DISTRICT LGD":753,"BLOCK LGD":4834,"STATE":"Andhra Pradesh","DISTRICT":"Annamayya"},{"BLOCK":"Lalganj","Latitude":25.865582,"Longitude":85.1639734,"STATE LGD":10,"DISTRICT LGD":224,"BLOCK LGD":2144,"STATE":"Bihar","DISTRICT":"Vaishali"},{"BLOCK":"Lalgola","Latitude":24.417134,"Longitude":88.2104289,"STATE LGD":19,"DISTRICT LGD":319,"BLOCK LGD":3015,"STATE":"West Bengal","DISTRICT":"Murshidabad"},{"BLOCK":"Lamka South","Latitude":24.2925924,"Longitude":93.6056779,"STATE LGD":14,"DISTRICT LGD":254,"BLOCK LGD":7316,"STATE":"Manipur","DISTRICT":"Churachandpur"},{"BLOCK":"Lamtaput","Latitude":18.86249,"Longitude":82.8657852,"STATE LGD":21,"DISTRICT LGD":363,"BLOCK LGD":3474,"STATE":"Odisha","DISTRICT":"Koraput"},{"BLOCK":"Laxmipur","Latitude":24.9052917,"Longitude":85.8998513,"STATE LGD":10,"DISTRICT LGD":198,"BLOCK LGD":1777,"STATE":"Bihar","DISTRICT":"Jamui"},{"BLOCK":"Laxmipur","Latitude":18.991636,"Longitude":83.1058538,"STATE LGD":21,"DISTRICT LGD":363,"BLOCK LGD":3475,"STATE":"Odisha","DISTRICT":"Koraput"},{"BLOCK":"Littipara","Latitude":24.6978525,"Longitude":87.5980641,"STATE LGD":20,"DISTRICT LGD":337,"BLOCK LGD":3200,"STATE":"Jharkhand","DISTRICT":"Pakur"},{"BLOCK":"Loharu","Latitude":28.426965,"Longitude":75.7935034,"STATE LGD":6,"DISTRICT LGD":59,"BLOCK LGD":460,"STATE":"Haryana","DISTRICT":"Bhiwani"},{"BLOCK":"Lungsen","Latitude":22.873802,"Longitude":92.5778388,"STATE LGD":15,"DISTRICT LGD":265,"BLOCK LGD":2403,"STATE":"Mizoram","DISTRICT":"Lunglei"},{"BLOCK":"Machhali Sahar","Latitude":25.6691354,"Longitude":82.1660986,"STATE LGD":9,"DISTRICT LGD":152,"BLOCK LGD":1232,"STATE":"Uttar Pradesh","DISTRICT":"Jaunpur"},{"BLOCK":"Madanpur","Latitude":24.6575855,"Longitude":84.5588705,"STATE LGD":10,"DISTRICT LGD":189,"BLOCK LGD":1640,"STATE":"Bihar","DISTRICT":"Aurangabad"},{"BLOCK":"Madanpur Rampur","Latitude":20.1936437,"Longitude":83.5064788,"STATE LGD":21,"DISTRICT LGD":358,"BLOCK LGD":3419,"STATE":"Odisha","DISTRICT":"Kalahandi"},{"BLOCK":"Maddikera (East)","Latitude":15.2486141,"Longitude":77.3694399,"STATE LGD":28,"DISTRICT LGD":511,"BLOCK LGD":5179,"STATE":"Andhra Pradesh","DISTRICT":"Kurnool"},{"BLOCK":"Magra Hat-2","Latitude":22.2398264,"Longitude":88.3682958,"STATE LGD":19,"DISTRICT LGD":304,"BLOCK LGD":2765,"STATE":"West Bengal","DISTRICT":"24 Paraganas South"},{"BLOCK":"Maheshtala","Latitude":22.5112091,"Longitude":88.2006157,"STATE LGD":19,"DISTRICT LGD":304,"BLOCK LGD":250300,"STATE":"West Bengal","DISTRICT":"24 Paraganas South"},{"BLOCK":"Mahuadanr","Latitude":23.3959491,"Longitude":84.0871719,"STATE LGD":20,"DISTRICT LGD":335,"BLOCK LGD":3191,"STATE":"Jharkhand","DISTRICT":"Latehar"},{"BLOCK":"Mainpur","Latitude":20.1332242,"Longitude":82.2913424,"STATE LGD":22,"DISTRICT LGD":645,"BLOCK LGD":3704,"STATE":"Chhattisgarh","DISTRICT":"Gariyaband"},{"BLOCK":"Majhgawan","Latitude":24.9162917,"Longitude":80.7955597,"STATE LGD":23,"DISTRICT LGD":426,"BLOCK LGD":3976,"STATE":"Madhya Pradesh","DISTRICT":"Satna"},{"BLOCK":"Makdi","Latitude":19.7808186,"Longitude":81.8966097,"STATE LGD":22,"DISTRICT LGD":643,"BLOCK LGD":3599,"STATE":"Chhattisgarh","DISTRICT":"Kondagaon"},{"BLOCK":"Makhu","Latitude":31.1075387,"Longitude":74.9694676,"STATE LGD":3,"DISTRICT LGD":31,"BLOCK LGD":248,"STATE":"Punjab","DISTRICT":"Ferozpur"},{"BLOCK":"Malegaon","Latitude":20.4563248,"Longitude":77.4973103,"STATE LGD":27,"DISTRICT LGD":499,"BLOCK LGD":4613,"STATE":"Maharashtra","DISTRICT":"Washim"},{"BLOCK":"Mananthavady","Latitude":11.800861,"Longitude":75.9634988,"STATE LGD":32,"DISTRICT LGD":567,"BLOCK LGD":6099,"STATE":"Kerala","DISTRICT":"Wayanad"},{"BLOCK":"Mandar","Latitude":23.4603626,"Longitude":85.0862789,"STATE LGD":20,"DISTRICT LGD":339,"BLOCK LGD":3227,"STATE":"Jharkhand","DISTRICT":"Ranchi"},{"BLOCK":"Mandawra","Latitude":24.6549228,"Longitude":78.198106,"STATE LGD":9,"DISTRICT LGD":161,"BLOCK LGD":1326,"STATE":"Uttar Pradesh","DISTRICT":"Lalitpur"},{"BLOCK":"Mandia","Latitude":26.2683166,"Longitude":90.9561002,"STATE LGD":18,"DISTRICT LGD":280,"BLOCK LGD":2497,"STATE":"Assam","DISTRICT":"Barpeta"},{"BLOCK":"Mandro","Latitude":25.1393627,"Longitude":87.5020282,"STATE LGD":20,"DISTRICT LGD":340,"BLOCK LGD":3240,"STATE":"Jharkhand","DISTRICT":"Sahebganj"},{"BLOCK":"Manihari","Latitude":25.3407556,"Longitude":87.6173932,"STATE LGD":10,"DISTRICT LGD":201,"BLOCK LGD":1810,"STATE":"Bihar","DISTRICT":"Katihar"},{"BLOCK":"Manjhanpur","Latitude":25.531809,"Longitude":81.3695686,"STATE LGD":9,"DISTRICT LGD":158,"BLOCK LGD":1289,"STATE":"Uttar Pradesh","DISTRICT":"Kaushambi"},{"BLOCK":"Manjhiaon","Latitude":24.3223544,"Longitude":83.8113713,"STATE LGD":20,"DISTRICT LGD":328,"BLOCK LGD":3125,"STATE":"Jharkhand","DISTRICT":"Garhwa"},{"BLOCK":"Mankote","Latitude":33.5929448,"Longitude":74.0764303,"STATE LGD":1,"DISTRICT LGD":10,"BLOCK LGD":6966,"STATE":"Jammu & Kashmir","DISTRICT":"Poonch"},{"BLOCK":"Manpur","Latitude":23.7675639,"Longitude":81.1208152,"STATE LGD":23,"DISTRICT LGD":436,"BLOCK LGD":4040,"STATE":"Madhya Pradesh","DISTRICT":"Umaria"},{"BLOCK":"Mansurchak","Latitude":25.625643,"Longitude":85.9066056,"STATE LGD":10,"DISTRICT LGD":191,"BLOCK LGD":1667,"STATE":"Bihar","DISTRICT":"Begusarai"},{"BLOCK":"Manzgam","Latitude":33.5948656,"Longitude":74.8543153,"STATE LGD":1,"DISTRICT LGD":622,"BLOCK LGD":6890,"STATE":"Jammu & Kashmir","DISTRICT":"Kulgam"},{"BLOCK":"Maredumilli","Latitude":17.7181645,"Longitude":81.6757246,"STATE LGD":28,"DISTRICT LGD":745,"BLOCK LGD":4895,"STATE":"Andhra Pradesh","DISTRICT":"Alluri Sitharama Raju"},{"BLOCK":"Marihan","Latitude":24.9140175,"Longitude":82.6751903,"STATE LGD":9,"DISTRICT LGD":170,"BLOCK LGD":1002,"STATE":"Uttar Pradesh","DISTRICT":"Mirzapur"},{"BLOCK":"Markacho","Latitude":24.3265481,"Longitude":85.8245086,"STATE LGD":20,"DISTRICT LGD":334,"BLOCK LGD":3184,"STATE":"Jharkhand","DISTRICT":"Koderma"},{"BLOCK":"Marwah","Latitude":33.3115951,"Longitude":75.7636446,"STATE LGD":1,"DISTRICT LGD":620,"BLOCK LGD":49,"STATE":"Jammu & Kashmir","DISTRICT":"Kishtwar"},{"BLOCK":"Masalpur","Latitude":26.6334797,"Longitude":77.2201222,"STATE LGD":8,"DISTRICT LGD":108,"BLOCK LGD":7403,"STATE":"Rajasthan","DISTRICT":"Karauli"},{"BLOCK":"Maski","Latitude":15.952165,"Longitude":76.6355747,"STATE LGD":29,"DISTRICT LGD":546,"BLOCK LGD":7414,"STATE":"Karnataka","DISTRICT":"Raichur"},{"BLOCK":"Mathili","Latitude":18.5466896,"Longitude":82.2048252,"STATE LGD":21,"DISTRICT LGD":364,"BLOCK LGD":3485,"STATE":"Odisha","DISTRICT":"Malkangiri"},{"BLOCK":"Mavai","Latitude":22.4965799,"Longitude":81.0712872,"STATE LGD":23,"DISTRICT LGD":415,"BLOCK LGD":3904,"STATE":"Madhya Pradesh","DISTRICT":"Mandla"},{"BLOCK":"Mayureswar-1","Latitude":24.0491604,"Longitude":87.6768076,"STATE LGD":19,"DISTRICT LGD":307,"BLOCK LGD":2832,"STATE":"West Bengal","DISTRICT":"Birbhum"},{"BLOCK":"Mayurhand","Latitude":24.2699062,"Longitude":85.2111726,"STATE LGD":20,"DISTRICT LGD":323,"BLOCK LGD":6691,"STATE":"Jharkhand","DISTRICT":"Chatra"},{"BLOCK":"Meghnagar","Latitude":22.9070895,"Longitude":74.5356739,"STATE LGD":23,"DISTRICT LGD":412,"BLOCK LGD":3878,"STATE":"Madhya Pradesh","DISTRICT":"Jhabua"},{"BLOCK":"Mehndwani","Latitude":22.9368998,"Longitude":80.6530058,"STATE LGD":23,"DISTRICT LGD":404,"BLOCK LGD":3833,"STATE":"Madhya Pradesh","DISTRICT":"Dindori"},{"BLOCK":"Melaneelithanallur","Latitude":9.1077643,"Longitude":77.5946331,"STATE LGD":33,"DISTRICT LGD":733,"BLOCK LGD":6393,"STATE":"Tamil Nadu","DISTRICT":"Tenkasi"},{"BLOCK":"Mithaura","Latitude":27.2379088,"Longitude":83.6658603,"STATE LGD":9,"DISTRICT LGD":164,"BLOCK LGD":1349,"STATE":"Uttar Pradesh","DISTRICT":"Maharajganj"},{"BLOCK":"Mori","Latitude":31.0195543,"Longitude":78.0417251,"STATE LGD":5,"DISTRICT LGD":57,"BLOCK LGD":444,"STATE":"Uttarakhand","DISTRICT":"Uttar Kashi"},{"BLOCK":"Mundgod","Latitude":14.9721488,"Longitude":75.0286173,"STATE LGD":29,"DISTRICT LGD":550,"BLOCK LGD":5924,"STATE":"Karnataka","DISTRICT":"Uttara Kannada"},{"BLOCK":"Muniguda","Latitude":19.6214469,"Longitude":83.4888195,"STATE LGD":21,"DISTRICT LGD":370,"BLOCK LGD":3554,"STATE":"Odisha","DISTRICT":"Raygada"},{"BLOCK":"Murgkongselek","Latitude":27.6553728,"Longitude":94.5583812,"STATE LGD":18,"DISTRICT LGD":284,"BLOCK LGD":2548,"STATE":"Assam","DISTRICT":"Dhemaji"},{"BLOCK":"Musabani","Latitude":22.5062007,"Longitude":86.4361496,"STATE LGD":20,"DISTRICT LGD":327,"BLOCK LGD":3114,"STATE":"Jharkhand","DISTRICT":"East Singhbum"},{"BLOCK":"Mushahari","Latitude":26.2187605,"Longitude":85.1095452,"STATE LGD":10,"DISTRICT LGD":208,"BLOCK LGD":1889,"STATE":"Bihar","DISTRICT":"Muzaffarpur"},{"BLOCK":"Mutharam (Mahadevpur)","Latitude":18.5308453,"Longitude":80.0127839,"STATE LGD":36,"DISTRICT LGD":687,"BLOCK LGD":5034,"STATE":"Telangana","DISTRICT":"Jayashankar Bhupalapally"},{"BLOCK":"Nabinagar","Latitude":24.6068101,"Longitude":84.1171626,"STATE LGD":10,"DISTRICT LGD":189,"BLOCK LGD":1641,"STATE":"Bihar","DISTRICT":"Aurangabad"},{"BLOCK":"Nahar","Latitude":28.409945,"Longitude":76.3930464,"STATE LGD":6,"DISTRICT LGD":72,"BLOCK LGD":539,"STATE":"Haryana","DISTRICT":"Rewari"},{"BLOCK":"Najibabad","Latitude":29.6070154,"Longitude":78.3235926,"STATE LGD":9,"DISTRICT LGD":132,"BLOCK LGD":996,"STATE":"Uttar Pradesh","DISTRICT":"Bijanaur"},{"BLOCK":"Naktideol","Latitude":21.2329251,"Longitude":84.5154903,"STATE LGD":21,"DISTRICT LGD":371,"BLOCK LGD":3564,"STATE":"Odisha","DISTRICT":"Sambalpur"},{"BLOCK":"Namchi","Latitude":27.1654137,"Longitude":88.3447978,"STATE LGD":11,"DISTRICT LGD":227,"BLOCK LGD":2157,"STATE":"Sikkim","DISTRICT":"Namchi"},{"BLOCK":"Nancowrie","Latitude":7.9784864,"Longitude":93.5026132,"STATE LGD":35,"DISTRICT LGD":603,"BLOCK LGD":6500,"STATE":"Andaman And Nicobar Islands","DISTRICT":"Nicobar"},{"BLOCK":"Nandod","Latitude":21.841882,"Longitude":73.3138938,"STATE LGD":24,"DISTRICT LGD":452,"BLOCK LGD":4176,"STATE":"Gujarat","DISTRICT":"Narmada"},{"BLOCK":"Nanguneri","Latitude":8.4984359,"Longitude":77.6318719,"STATE LGD":33,"DISTRICT LGD":592,"BLOCK LGD":6394,"STATE":"Tamil Nadu","DISTRICT":"Tirunelveli"},{"BLOCK":"Nanoor","Latitude":23.7026147,"Longitude":87.8550266,"STATE LGD":19,"DISTRICT LGD":307,"BLOCK LGD":2839,"STATE":"West Bengal","DISTRICT":"Birbhum"},{"BLOCK":"Narayanganj","Latitude":22.8271694,"Longitude":80.2269103,"STATE LGD":23,"DISTRICT LGD":415,"BLOCK LGD":3907,"STATE":"Madhya Pradesh","DISTRICT":"Mandla"},{"BLOCK":"Narnoor","Latitude":19.5017498,"Longitude":78.8456797,"STATE LGD":36,"DISTRICT LGD":501,"BLOCK LGD":4670,"STATE":"Telangana","DISTRICT":"Adilabad"},{"BLOCK":"Narva","Latitude":16.4625696,"Longitude":77.5089277,"STATE LGD":36,"DISTRICT LGD":721,"BLOCK LGD":5250,"STATE":"Telangana","DISTRICT":"Narayanpet"},{"BLOCK":"Naswadi","Latitude":22.0454299,"Longitude":73.7202357,"STATE LGD":24,"DISTRICT LGD":668,"BLOCK LGD":4262,"STATE":"Gujarat","DISTRICT":"Chhotaudepur"},{"BLOCK":"Navapur","Latitude":21.1587955,"Longitude":73.7684486,"STATE LGD":27,"DISTRICT LGD":486,"BLOCK LGD":4476,"STATE":"Maharashtra","DISTRICT":"Nandurbar"},{"BLOCK":"Nawabganj","Latitude":27.4500182,"Longitude":79.4063672,"STATE LGD":9,"DISTRICT LGD":141,"BLOCK LGD":1100,"STATE":"Uttar Pradesh","DISTRICT":"Farrukhabad"},{"BLOCK":"Neemrana","Latitude":27.9764728,"Longitude":76.367197,"STATE LGD":8,"DISTRICT LGD":87,"BLOCK LGD":581,"STATE":"Rajasthan","DISTRICT":"Alwar"},{"BLOCK":"New Sangbar","Latitude":25.3300246,"Longitude":92.9289322,"STATE LGD":18,"DISTRICT LGD":299,"BLOCK LGD":2692,"STATE":"Assam","DISTRICT":"Dima Hasao"},{"BLOCK":"Ngopa","Latitude":23.6897448,"Longitude":92.9559015,"STATE LGD":15,"DISTRICT LGD":727,"BLOCK LGD":2394,"STATE":"Mizoram","DISTRICT":"Saitual"},{"BLOCK":"Nihal Singh Wala","Latitude":30.5915783,"Longitude":75.2707456,"STATE LGD":3,"DISTRICT LGD":38,"BLOCK LGD":313,"STATE":"Punjab","DISTRICT":"Moga"},{"BLOCK":"Nilip","Latitude":26.4234875,"Longitude":93.7432687,"STATE LGD":18,"DISTRICT LGD":292,"BLOCK LGD":2622,"STATE":"Assam","DISTRICT":"Karbi Anglong"},{"BLOCK":"Nimbhahera","Latitude":24.6247251,"Longitude":74.6413588,"STATE LGD":8,"DISTRICT LGD":95,"BLOCK LGD":651,"STATE":"Rajasthan","DISTRICT":"Chittorgarh"},{"BLOCK":"Nindaura","Latitude":27.1187966,"Longitude":81.0516002,"STATE LGD":9,"DISTRICT LGD":129,"BLOCK LGD":951,"STATE":"Uttar Pradesh","DISTRICT":"Barabanki"},{"BLOCK":"Nirmand","Latitude":31.4217227,"Longitude":77.5675964,"STATE LGD":2,"DISTRICT LGD":20,"BLOCK LGD":172,"STATE":"Himachal Pradesh","DISTRICT":"Kullu"},{"BLOCK":"Nizar","Latitude":21.4765783,"Longitude":74.1874202,"STATE LGD":24,"DISTRICT LGD":641,"BLOCK LGD":4238,"STATE":"Gujarat","DISTRICT":"Tapi"},{"BLOCK":"Nuagaon","Latitude":22.3891634,"Longitude":84.9042304,"STATE LGD":21,"DISTRICT LGD":373,"BLOCK LGD":3585,"STATE":"Odisha","DISTRICT":"Sundargarh"},{"BLOCK":"Nuh","Latitude":22.3891634,"Longitude":84.9042304,"STATE LGD":6,"DISTRICT LGD":604,"BLOCK LGD":479,"STATE":"Haryana","DISTRICT":"Nuh"},{"BLOCK":"Onda","Latitude":23.1434161,"Longitude":87.1839377,"STATE LGD":19,"DISTRICT LGD":305,"BLOCK LGD":2786,"STATE":"West Bengal","DISTRICT":"Bankura"},{"BLOCK":"Orchha","Latitude":19.5444449,"Longitude":81.0250891,"STATE LGD":22,"DISTRICT LGD":637,"BLOCK LGD":3601,"STATE":"Chhattisgarh","DISTRICT":"Narayanpur"},{"BLOCK":"Padmapur","Latitude":19.2390056,"Longitude":83.8129806,"STATE LGD":21,"DISTRICT LGD":370,"BLOCK LGD":3555,"STATE":"Odisha","DISTRICT":"Raygada"},{"BLOCK":"Pahadgarh","Latitude":26.1866171,"Longitude":77.6477953,"STATE LGD":23,"DISTRICT LGD":417,"BLOCK LGD":3918,"STATE":"Madhya Pradesh","DISTRICT":"Morena"},{"BLOCK":"Paikamal","Latitude":20.9270406,"Longitude":82.8033219,"STATE LGD":21,"DISTRICT LGD":347,"BLOCK LGD":3320,"STATE":"Odisha","DISTRICT":"Bargarh"},{"BLOCK":"Pakri Barawan","Latitude":24.9516384,"Longitude":85.728481,"STATE LGD":10,"DISTRICT LGD":210,"BLOCK LGD":1923,"STATE":"Bihar","DISTRICT":"Nawada"},{"BLOCK":"Palasi","Latitude":26.2385721,"Longitude":87.5551352,"STATE LGD":10,"DISTRICT LGD":188,"BLOCK LGD":1630,"STATE":"Bihar","DISTRICT":"Araria"},{"BLOCK":"Pali 1 (Gohparu)","Latitude":23.4403378,"Longitude":81.0550398,"STATE LGD":23,"DISTRICT LGD":429,"BLOCK LGD":3997,"STATE":"Madhya Pradesh","DISTRICT":"Shahdol"},{"BLOCK":"Palimela","Latitude":17.121755,"Longitude":79.0135554,"STATE LGD":36,"DISTRICT LGD":687,"BLOCK LGD":7210,"STATE":"Telangana","DISTRICT":"Jayashankar Bhupalapally"},{"BLOCK":"Panamaram","Latitude":11.7405274,"Longitude":76.0538861,"STATE LGD":32,"DISTRICT LGD":567,"BLOCK LGD":6693,"STATE":"Kerala","DISTRICT":"Wayanad"},{"BLOCK":"Pandari Kripal","Latitude":27.1788237,"Longitude":81.9828002,"STATE LGD":9,"DISTRICT LGD":147,"BLOCK LGD":1164,"STATE":"Uttar Pradesh","DISTRICT":"Gonda"},{"BLOCK":"Pangi","Latitude":32.9881821,"Longitude":76.5200422,"STATE LGD":2,"DISTRICT LGD":16,"BLOCK LGD":142,"STATE":"Himachal Pradesh","DISTRICT":"Chamba"},{"BLOCK":"Paranda","Latitude":18.2661222,"Longitude":75.4428774,"STATE LGD":27,"DISTRICT LGD":488,"BLOCK LGD":4499,"STATE":"Maharashtra","DISTRICT":"Osmanabad"},{"BLOCK":"Parappa","Latitude":12.3694513,"Longitude":75.2339242,"STATE LGD":32,"DISTRICT LGD":558,"BLOCK LGD":6696,"STATE":"Kerala","DISTRICT":"Kasargod"},{"BLOCK":"Parbatta","Latitude":25.3188023,"Longitude":86.713764,"STATE LGD":10,"DISTRICT LGD":202,"BLOCK LGD":1820,"STATE":"Bihar","DISTRICT":"Khagaria"},{"BLOCK":"Partur","Latitude":19.5887393,"Longitude":76.1947772,"STATE LGD":27,"DISTRICT LGD":479,"BLOCK LGD":4418,"STATE":"Maharashtra","DISTRICT":"Jalna"},{"BLOCK":"Pati","Latitude":21.9410374,"Longitude":74.7414378,"STATE LGD":23,"DISTRICT LGD":393,"BLOCK LGD":3757,"STATE":"Madhya Pradesh","DISTRICT":"Barwani"},{"BLOCK":"Patratu","Latitude":23.6372765,"Longitude":85.2556217,"STATE LGD":20,"DISTRICT LGD":607,"BLOCK LGD":3174,"STATE":"Jharkhand","DISTRICT":"Ramgarh"},{"BLOCK":"Peepal Khoont","Latitude":23.8083181,"Longitude":74.5510601,"STATE LGD":8,"DISTRICT LGD":629,"BLOCK LGD":594,"STATE":"Rajasthan","DISTRICT":"Pratapgarh"},{"BLOCK":"Peeplu","Latitude":26.2971098,"Longitude":75.6931783,"STATE LGD":8,"DISTRICT LGD":116,"BLOCK LGD":7464,"STATE":"Rajasthan","DISTRICT":"Tonk"},{"BLOCK":"Pembi","Latitude":19.19511,"Longitude":78.6325943,"STATE LGD":36,"DISTRICT LGD":680,"BLOCK LGD":7199,"STATE":"Telangana","DISTRICT":"Nirmal"},{"BLOCK":"Penuganchiprolu","Latitude":16.8632415,"Longitude":80.1681084,"STATE LGD":28,"DISTRICT LGD":749,"BLOCK LGD":5138,"STATE":"Andhra Pradesh","DISTRICT":"NTR"},{"BLOCK":"Phiringia","Latitude":20.3607649,"Longitude":84.0967855,"STATE LGD":21,"DISTRICT LGD":359,"BLOCK LGD":3429,"STATE":"Odisha","DISTRICT":"Kandhamal"},{"BLOCK":"Pichore","Latitude":25.1786576,"Longitude":78.1626817,"STATE LGD":23,"DISTRICT LGD":432,"BLOCK LGD":4016,"STATE":"Madhya Pradesh","DISTRICT":"Shivpuri"},{"BLOCK":"Pirpainti","Latitude":25.3222196,"Longitude":87.4170852,"STATE LGD":10,"DISTRICT LGD":192,"BLOCK LGD":1683,"STATE":"Bihar","DISTRICT":"Bhagalpur"},{"BLOCK":"Pithora","Latitude":21.2556013,"Longitude":82.4996331,"STATE LGD":22,"DISTRICT LGD":385,"BLOCK LGD":3682,"STATE":"Chhattisgarh","DISTRICT":"Mahasamund"},{"BLOCK":"Podi Uproda","Latitude":22.5797929,"Longitude":82.5097216,"STATE LGD":22,"DISTRICT LGD":383,"BLOCK LGD":3673,"STATE":"Chhattisgarh","DISTRICT":"Korba"},{"BLOCK":"Pongchau","Latitude":26.7227485,"Longitude":95.2654267,"STATE LGD":12,"DISTRICT LGD":666,"BLOCK LGD":6794,"STATE":"Arunachal Pradesh","DISTRICT":"Longding"},{"BLOCK":"Pooh","Latitude":31.76343,"Longitude":78.5864924,"STATE LGD":2,"DISTRICT LGD":19,"BLOCK LGD":167,"STATE":"Himachal Pradesh","DISTRICT":"Kinnaur"},{"BLOCK":"Pratappur","Latitude":23.4853067,"Longitude":83.1903862,"STATE LGD":22,"DISTRICT LGD":648,"BLOCK LGD":3726,"STATE":"Chhattisgarh","DISTRICT":"Surajpur"},{"BLOCK":"Prithvipur","Latitude":25.2192169,"Longitude":78.70905,"STATE LGD":23,"DISTRICT LGD":722,"BLOCK LGD":4031,"STATE":"Madhya Pradesh","DISTRICT":"Niwari"},{"BLOCK":"Pub-Mangaldai","Latitude":26.4691522,"Longitude":92.0252195,"STATE LGD":18,"DISTRICT LGD":283,"BLOCK LGD":2537,"STATE":"Assam","DISTRICT":"Darrang"},{"BLOCK":"Puintala","Latitude":20.716711,"Longitude":83.5066938,"STATE LGD":21,"DISTRICT LGD":345,"BLOCK LGD":3294,"STATE":"Odisha","DISTRICT":"Balangir"},{"BLOCK":"Punhana","Latitude":27.8657829,"Longitude":77.1946835,"STATE LGD":6,"DISTRICT LGD":604,"BLOCK LGD":481,"STATE":"Haryana","DISTRICT":"Nuh"},{"BLOCK":"Puranpur","Latitude":28.5127462,"Longitude":80.1383024,"STATE LGD":9,"DISTRICT LGD":173,"BLOCK LGD":1445,"STATE":"Uttar Pradesh","DISTRICT":"Pilbhit"},{"BLOCK":"Puredalai","Latitude":26.894853,"Longitude":81.2820391,"STATE LGD":9,"DISTRICT LGD":129,"BLOCK LGD":952,"STATE":"Uttar Pradesh","DISTRICT":"Barabanki"},{"BLOCK":"Pusad","Latitude":19.9093591,"Longitude":77.5221479,"STATE LGD":27,"DISTRICT LGD":500,"BLOCK LGD":4628,"STATE":"Maharashtra","DISTRICT":"Yavatmal"},{"BLOCK":"Pushprajgarh","Latitude":22.9885406,"Longitude":81.1296051,"STATE LGD":23,"DISTRICT LGD":390,"BLOCK LGD":3739,"STATE":"Madhya Pradesh","DISTRICT":"Anuppur"},{"BLOCK":"R. Udaygiri","Latitude":19.1601878,"Longitude":84.1346846,"STATE LGD":21,"DISTRICT LGD":353,"BLOCK LGD":3362,"STATE":"Odisha","DISTRICT":"Gajapati"},{"BLOCK":"Rajepur","Latitude":27.4800721,"Longitude":79.6568441,"STATE LGD":9,"DISTRICT LGD":141,"BLOCK LGD":1101,"STATE":"Uttar Pradesh","DISTRICT":"Farrukhabad"},{"BLOCK":"Rajgarh","Latitude":28.6358499,"Longitude":75.3641079,"STATE LGD":8,"DISTRICT LGD":96,"BLOCK LGD":655,"STATE":"Rajasthan","DISTRICT":"Churu"},{"BLOCK":"Ram Pur","Latitude":25.483539,"Longitude":82.5737752,"STATE LGD":9,"DISTRICT LGD":152,"BLOCK LGD":1238,"STATE":"Uttar Pradesh","DISTRICT":"Jaunpur"},{"BLOCK":"Rama","Latitude":22.7845632,"Longitude":74.7021103,"STATE LGD":23,"DISTRICT LGD":412,"BLOCK LGD":3880,"STATE":"Madhya Pradesh","DISTRICT":"Jhabua"},{"BLOCK":"Ramgarh","Latitude":24.9653256,"Longitude":83.558025,"STATE LGD":10,"DISTRICT LGD":200,"BLOCK LGD":1796,"STATE":"Bihar","DISTRICT":"Kaimur (Bhabua)"},{"BLOCK":"Ramgarh","Latitude":24.5619362,"Longitude":87.240672,"STATE LGD":20,"DISTRICT LGD":326,"BLOCK LGD":3104,"STATE":"Jharkhand","DISTRICT":"Dumka"},{"BLOCK":"Ramgarh Pachwara","Latitude":26.6322119,"Longitude":76.2371703,"STATE LGD":8,"DISTRICT LGD":97,"BLOCK LGD":7444,"STATE":"Rajasthan","DISTRICT":"Dausa"},{"BLOCK":"Ramnagar","Latitude":25.2901392,"Longitude":79.8544673,"STATE LGD":9,"DISTRICT LGD":136,"BLOCK LGD":1046,"STATE":"Uttar Pradesh","DISTRICT":"Chitrakoot"},{"BLOCK":"Rampur","Latitude":25.1496361,"Longitude":83.5687254,"STATE LGD":10,"DISTRICT LGD":200,"BLOCK LGD":1797,"STATE":"Bihar","DISTRICT":"Kaimur (Bhabua)"},{"BLOCK":"Rampur Baghelan","Latitude":24.5093966,"Longitude":81.0478862,"STATE LGD":23,"DISTRICT LGD":426,"BLOCK LGD":3979,"STATE":"Madhya Pradesh","DISTRICT":"Satna"},{"BLOCK":"Rampura","Latitude":26.3364688,"Longitude":79.3602502,"STATE LGD":9,"DISTRICT LGD":151,"BLOCK LGD":1222,"STATE":"Uttar Pradesh","DISTRICT":"Jalaun"},{"BLOCK":"Ramsar","Latitude":25.7274987,"Longitude":70.8521172,"STATE LGD":8,"DISTRICT LGD":90,"BLOCK LGD":6843,"STATE":"Rajasthan","DISTRICT":"Barmer"},{"BLOCK":"Ranapur","Latitude":22.6475711,"Longitude":74.5158434,"STATE LGD":23,"DISTRICT LGD":412,"BLOCK LGD":3881,"STATE":"Madhya Pradesh","DISTRICT":"Jhabua"},{"BLOCK":"Rani Station","Latitude":25.3590875,"Longitude":73.2706905,"STATE LGD":8,"DISTRICT LGD":111,"BLOCK LGD":757,"STATE":"Rajasthan","DISTRICT":"Pali"},{"BLOCK":"Rapar","Latitude":23.5700044,"Longitude":70.6240955,"STATE LGD":24,"DISTRICT LGD":449,"BLOCK LGD":4155,"STATE":"Gujarat","DISTRICT":"Kachchh"},{"BLOCK":"Reiek","Latitude":23.6776795,"Longitude":92.5934171,"STATE LGD":15,"DISTRICT LGD":266,"BLOCK LGD":2404,"STATE":"Mizoram","DISTRICT":"Mamit"},{"BLOCK":"Resubelpara","Latitude":25.5928888,"Longitude":90.0288357,"STATE LGD":17,"DISTRICT LGD":656,"BLOCK LGD":2452,"STATE":"Meghalaya","DISTRICT":"Ngh (Garo Region)"},{"BLOCK":"Rithi","Latitude":23.9081829,"Longitude":80.1174353,"STATE LGD":23,"DISTRICT LGD":413,"BLOCK LGD":3889,"STATE":"Madhya Pradesh","DISTRICT":"Katni"},{"BLOCK":"Rongmongwe","Latitude":26.540712,"Longitude":93.2296374,"STATE LGD":18,"DISTRICT LGD":292,"BLOCK LGD":2624,"STATE":"Assam","DISTRICT":"Karbi Anglong"},{"BLOCK":"Rupaideeh","Latitude":27.2839716,"Longitude":81.9342403,"STATE LGD":9,"DISTRICT LGD":147,"BLOCK LGD":1166,"STATE":"Uttar Pradesh","DISTRICT":"Gonda"},{"BLOCK":"Rupsho","Latitude":33.9818271,"Longitude":74.8029823,"STATE LGD":37,"DISTRICT LGD":9,"BLOCK LGD":7047,"STATE":"Ladakh","DISTRICT":"Leh"},{"BLOCK":"Sabour","Latitude":25.2442373,"Longitude":87.0348569,"STATE LGD":10,"DISTRICT LGD":192,"BLOCK LGD":1685,"STATE":"Bihar","DISTRICT":"Bhagalpur"},{"BLOCK":"Saidnagar","Latitude":28.9044565,"Longitude":79.0019265,"STATE LGD":9,"DISTRICT LGD":176,"BLOCK LGD":1487,"STATE":"Uttar Pradesh","DISTRICT":"Rampur"},{"BLOCK":"Sajjangarh","Latitude":23.2594148,"Longitude":74.2826413,"STATE LGD":8,"DISTRICT LGD":88,"BLOCK LGD":595,"STATE":"Rajasthan","DISTRICT":"Banswara"},{"BLOCK":"Salbani","Latitude":22.6407879,"Longitude":87.3128448,"STATE LGD":19,"DISTRICT LGD":318,"BLOCK LGD":2999,"STATE":"West Bengal","DISTRICT":"Medinipur West"},{"BLOCK":"Samelangso","Latitude":26.2957931,"Longitude":93.1884813,"STATE LGD":18,"DISTRICT LGD":292,"BLOCK LGD":2625,"STATE":"Assam","DISTRICT":"Karbi Anglong"},{"BLOCK":"Samho Akha Kurha","Latitude":25.2721359,"Longitude":86.189413,"STATE LGD":10,"DISTRICT LGD":191,"BLOCK LGD":1671,"STATE":"Bihar","DISTRICT":"Begusarai"},{"BLOCK":"Sandesh","Latitude":25.4027509,"Longitude":84.730457,"STATE LGD":10,"DISTRICT LGD":193,"BLOCK LGD":1699,"STATE":"Bihar","DISTRICT":"Bhojpur"},{"BLOCK":"Sandila","Latitude":27.0648176,"Longitude":80.4901494,"STATE LGD":9,"DISTRICT LGD":150,"BLOCK LGD":1209,"STATE":"Uttar Pradesh","DISTRICT":"Hardoi"},{"BLOCK":"Sangaria","Latitude":29.7820378,"Longitude":74.4211308,"STATE LGD":8,"DISTRICT LGD":101,"BLOCK LGD":6615,"STATE":"Rajasthan","DISTRICT":"Hanumangarh"},{"BLOCK":"Sangola","Latitude":17.4373136,"Longitude":75.1694652,"STATE LGD":27,"DISTRICT LGD":496,"BLOCK LGD":4586,"STATE":"Maharashtra","DISTRICT":"Solapur"},{"BLOCK":"Santalpur","Latitude":23.7623789,"Longitude":71.1588763,"STATE LGD":24,"DISTRICT LGD":455,"BLOCK LGD":4200,"STATE":"Gujarat","DISTRICT":"Patan"},{"BLOCK":"Sarath","Latitude":24.2365356,"Longitude":86.8309163,"STATE LGD":20,"DISTRICT LGD":324,"BLOCK LGD":3088,"STATE":"Jharkhand","DISTRICT":"Deoghar"},{"BLOCK":"Sarwan","Latitude":24.3514725,"Longitude":86.6946649,"STATE LGD":20,"DISTRICT LGD":324,"BLOCK LGD":3089,"STATE":"Jharkhand","DISTRICT":"Deoghar"},{"BLOCK":"Sayla","Latitude":22.5492034,"Longitude":71.4752053,"STATE LGD":24,"DISTRICT LGD":460,"BLOCK LGD":4255,"STATE":"Gujarat","DISTRICT":"Surendranagar"},{"BLOCK":"Seraikella","Latitude":22.6999311,"Longitude":85.9187318,"STATE LGD":20,"DISTRICT LGD":341,"BLOCK LGD":3253,"STATE":"Jharkhand","DISTRICT":"Saraikela Kharsawan"},{"BLOCK":"Shahbadha","Latitude":17.1321348,"Longitude":76.9223639,"STATE LGD":29,"DISTRICT LGD":538,"BLOCK LGD":7408,"STATE":"Karnataka","DISTRICT":"Kalburgi"},{"BLOCK":"Shahkot","Latitude":31.0836987,"Longitude":75.3173194,"STATE LGD":3,"DISTRICT LGD":34,"BLOCK LGD":286,"STATE":"Punjab","DISTRICT":"Jalandhar"},{"BLOCK":"Shahpur","Latitude":25.5858605,"Longitude":84.4422943,"STATE LGD":10,"DISTRICT LGD":193,"BLOCK LGD":1700,"STATE":"Bihar","DISTRICT":"Bhojpur"},{"BLOCK":"Shakargarh","Latitude":23.2889243,"Longitude":83.6632206,"STATE LGD":22,"DISTRICT LGD":649,"BLOCK LGD":3731,"STATE":"Chhattisgarh","DISTRICT":"Balrampur"},{"BLOCK":"Sheikhopur Sarai","Latitude":25.4282917,"Longitude":84.4374916,"STATE LGD":10,"DISTRICT LGD":219,"BLOCK LGD":2083,"STATE":"Bihar","DISTRICT":"Sheikhpura"},{"BLOCK":"Sheopur","Latitude":25.6701456,"Longitude":76.6760942,"STATE LGD":23,"DISTRICT LGD":431,"BLOCK LGD":4009,"STATE":"Madhya Pradesh","DISTRICT":"Sheopur"},{"BLOCK":"Shergarh","Latitude":26.3247098,"Longitude":72.2850179,"STATE LGD":8,"DISTRICT LGD":107,"BLOCK LGD":729,"STATE":"Rajasthan","DISTRICT":"Jodhpur"},{"BLOCK":"Shriduttganj","Latitude":27.3751678,"Longitude":82.3021373,"STATE LGD":9,"DISTRICT LGD":127,"BLOCK LGD":931,"STATE":"Uttar Pradesh","DISTRICT":"Balrampur"},{"BLOCK":"Shukul Bazar","Latitude":26.3843609,"Longitude":81.3653917,"STATE LGD":9,"DISTRICT LGD":640,"BLOCK LGD":1599,"STATE":"Uttar Pradesh","DISTRICT":"Amethi"},{"BLOCK":"Singhpora","Latitude":34.1504272,"Longitude":74.6065862,"STATE LGD":1,"DISTRICT LGD":3,"BLOCK LGD":30,"STATE":"Jammu & Kashmir","DISTRICT":"Baramulla"},{"BLOCK":"Sirivara","Latitude":16.1749613,"Longitude":77.0166886,"STATE LGD":29,"DISTRICT LGD":546,"BLOCK LGD":7415,"STATE":"Karnataka","DISTRICT":"Raichur"},{"BLOCK":"Sirmour","Latitude":24.5406797,"Longitude":81.2824771,"STATE LGD":23,"DISTRICT LGD":424,"BLOCK LGD":3961,"STATE":"Madhya Pradesh","DISTRICT":"Rewa"},{"BLOCK":"Sironcha","Latitude":18.846512,"Longitude":79.9549126,"STATE LGD":27,"DISTRICT LGD":475,"BLOCK LGD":4382,"STATE":"Maharashtra","DISTRICT":"Gadhichiroli"},{"BLOCK":"Socheng","Latitude":25.9314645,"Longitude":92.5518792,"STATE LGD":18,"DISTRICT LGD":710,"BLOCK LGD":2626,"STATE":"Assam","DISTRICT":"West Karbi Anglong"},{"BLOCK":"Sonhaula","Latitude":25.0884599,"Longitude":87.157993,"STATE LGD":10,"DISTRICT LGD":192,"BLOCK LGD":1687,"STATE":"Bihar","DISTRICT":"Bhagalpur"},{"BLOCK":"Sono","Latitude":24.7350137,"Longitude":86.2954392,"STATE LGD":10,"DISTRICT LGD":198,"BLOCK LGD":1779,"STATE":"Bihar","DISTRICT":"Jamui"},{"BLOCK":"South Hailakandi","Latitude":24.6798903,"Longitude":92.521956,"STATE LGD":18,"DISTRICT LGD":289,"BLOCK LGD":2590,"STATE":"Assam","DISTRICT":"Hailakandi"},{"BLOCK":"Srinagar","Latitude":25.9352747,"Longitude":87.38211,"STATE LGD":10,"DISTRICT LGD":214,"BLOCK LGD":2009,"STATE":"Bihar","DISTRICT":"Purnia"},{"BLOCK":"Subir","Latitude":20.9322838,"Longitude":73.7543403,"STATE LGD":24,"DISTRICT LGD":444,"BLOCK LGD":7109,"STATE":"Gujarat","DISTRICT":"Dang"},{"BLOCK":"Sultanganj","Latitude":25.2421719,"Longitude":86.7231979,"STATE LGD":10,"DISTRICT LGD":192,"BLOCK LGD":1688,"STATE":"Bihar","DISTRICT":"Bhagalpur"},{"BLOCK":"Sultanpur Lodhi","Latitude":31.2217843,"Longitude":75.1837605,"STATE LGD":3,"DISTRICT LGD":35,"BLOCK LGD":291,"STATE":"Punjab","DISTRICT":"Kapurthala"},{"BLOCK":"Sulthanbathery","Latitude":11.6519946,"Longitude":76.2154362,"STATE LGD":32,"DISTRICT LGD":567,"BLOCK LGD":6100,"STATE":"Kerala","DISTRICT":"Wayanad"},{"BLOCK":"Sundarpahari","Latitude":24.7798907,"Longitude":87.3233052,"STATE LGD":20,"DISTRICT LGD":330,"BLOCK LGD":3149,"STATE":"Jharkhand","DISTRICT":"Godda"},{"BLOCK":"Supa","Latitude":15.2692542,"Longitude":74.4995191,"STATE LGD":29,"DISTRICT LGD":550,"BLOCK LGD":5927,"STATE":"Karnataka","DISTRICT":"Uttara Kannada"},{"BLOCK":"Surajgarha","Latitude":25.2547849,"Longitude":86.2166688,"STATE LGD":10,"DISTRICT LGD":204,"BLOCK LGD":1834,"STATE":"Bihar","DISTRICT":"Lakhisarai"},{"BLOCK":"Surgana","Latitude":20.5587262,"Longitude":73.632321,"STATE LGD":27,"DISTRICT LGD":487,"BLOCK LGD":4491,"STATE":"Maharashtra","DISTRICT":"Nashik"},{"BLOCK":"Syaldey","Latitude":29.8230578,"Longitude":79.2044681,"STATE LGD":5,"DISTRICT LGD":45,"BLOCK LGD":360,"STATE":"Uttarakhand","DISTRICT":"Almora"},{"BLOCK":"Talasari","Latitude":20.1187292,"Longitude":72.8989102,"STATE LGD":27,"DISTRICT LGD":665,"BLOCK LGD":4598,"STATE":"Maharashtra","DISTRICT":"Palghar"},{"BLOCK":"Tali","Latitude":28.0033109,"Longitude":93.7013632,"STATE LGD":12,"DISTRICT LGD":677,"BLOCK LGD":2202,"STATE":"Arunachal Pradesh","DISTRICT":"Kra Daadi"},{"BLOCK":"Taloda","Latitude":21.559734,"Longitude":74.2045353,"STATE LGD":27,"DISTRICT LGD":486,"BLOCK LGD":4478,"STATE":"Maharashtra","DISTRICT":"Nandurbar"},{"BLOCK":"Tamulpur","Latitude":26.6424538,"Longitude":91.5640652,"STATE LGD":18,"DISTRICT LGD":616,"BLOCK LGD":2686,"STATE":"Assam","DISTRICT":"Tamulpur"},{"BLOCK":"Tanda","Latitude":26.5456247,"Longitude":82.6270997,"STATE LGD":9,"DISTRICT LGD":121,"BLOCK LGD":858,"STATE":"Uttar Pradesh","DISTRICT":"Ambedkar Nagar"},{"BLOCK":"Tarapur","Latitude":25.0948858,"Longitude":86.64395,"STATE LGD":10,"DISTRICT LGD":207,"BLOCK LGD":1876,"STATE":"Bihar","DISTRICT":"Munger"},{"BLOCK":"Teghra","Latitude":25.4881379,"Longitude":85.928673,"STATE LGD":10,"DISTRICT LGD":191,"BLOCK LGD":1672,"STATE":"Bihar","DISTRICT":"Begusarai"},{"BLOCK":"Tendukheda","Latitude":23.3908409,"Longitude":79.5273792,"STATE LGD":23,"DISTRICT LGD":400,"BLOCK LGD":3806,"STATE":"Madhya Pradesh","DISTRICT":"Damoh"},{"BLOCK":"Tentulikhunti","Latitude":19.2949623,"Longitude":82.7186607,"STATE LGD":21,"DISTRICT LGD":366,"BLOCK LGD":3521,"STATE":"Odisha","DISTRICT":"Nabarangapur"},{"BLOCK":"Thakrakote","Latitude":33.2346873,"Longitude":74.6608498,"STATE LGD":1,"DISTRICT LGD":627,"BLOCK LGD":6943,"STATE":"Jammu & Kashmir","DISTRICT":"Reasi"},{"BLOCK":"Thakurmunda","Latitude":21.5224295,"Longitude":86.1452577,"STATE LGD":21,"DISTRICT LGD":365,"BLOCK LGD":3510,"STATE":"Odisha","DISTRICT":"Mayurbhanj"},{"BLOCK":"Thalikoti","Latitude":16.8343295,"Longitude":75.7135633,"STATE LGD":29,"DISTRICT LGD":530,"BLOCK LGD":7398,"STATE":"Karnataka","DISTRICT":"Vijayapura"},{"BLOCK":"Thandla","Latitude":23.0137233,"Longitude":74.5549456,"STATE LGD":23,"DISTRICT LGD":412,"BLOCK LGD":3883,"STATE":"Madhya Pradesh","DISTRICT":"Jhabua"},{"BLOCK":"Tharad","Latitude":24.3927651,"Longitude":71.6088125,"STATE LGD":24,"DISTRICT LGD":441,"BLOCK LGD":4088,"STATE":"Gujarat","DISTRICT":"Banas Kantha"},{"BLOCK":"Thirupathur","Latitude":9.9804413,"Longitude":78.5345581,"STATE LGD":33,"DISTRICT LGD":585,"BLOCK LGD":6318,"STATE":"Tamil Nadu","DISTRICT":"Sivaganga"},{"BLOCK":"Thiruvadanai","Latitude":9.7826803,"Longitude":78.9136628,"STATE LGD":33,"DISTRICT LGD":583,"BLOCK LGD":6287,"STATE":"Tamil Nadu","DISTRICT":"Ramanathapuram"},{"BLOCK":"Thiruvarankulam","Latitude":10.3771855,"Longitude":78.8704863,"STATE LGD":33,"DISTRICT LGD":582,"BLOCK LGD":6274,"STATE":"Tamil Nadu","DISTRICT":"Pudhukottai"},{"BLOCK":"Thiruvennainallur","Latitude":11.8612093,"Longitude":79.3605565,"STATE LGD":33,"DISTRICT LGD":596,"BLOCK LGD":6468,"STATE":"Tamil Nadu","DISTRICT":"Villupuram"},{"BLOCK":"Thogaimalai","Latitude":10.7137302,"Longitude":78.4027067,"STATE LGD":33,"DISTRICT LGD":576,"BLOCK LGD":6204,"STATE":"Tamil Nadu","DISTRICT":"Karur"},{"BLOCK":"Thonoknyu","Latitude":25.9701982,"Longitude":94.8994414,"STATE LGD":13,"DISTRICT LGD":736,"BLOCK LGD":2348,"STATE":"Nagaland","DISTRICT":"Tuensang"},{"BLOCK":"Thuamul Rampur","Latitude":19.5469598,"Longitude":82.9191505,"STATE LGD":21,"DISTRICT LGD":358,"BLOCK LGD":3421,"STATE":"Odisha","DISTRICT":"Kalahandi"},{"BLOCK":"Tilouthu","Latitude":24.8096348,"Longitude":84.0796015,"STATE LGD":10,"DISTRICT LGD":215,"BLOCK LGD":2028,"STATE":"Bihar","DISTRICT":"Rohtas"},{"BLOCK":"Timri","Latitude":12.8311937,"Longitude":79.2933072,"STATE LGD":33,"DISTRICT LGD":731,"BLOCK LGD":6449,"STATE":"Tamil Nadu","DISTRICT":"Ranipet"},{"BLOCK":"Tiriyani","Latitude":17.4735694,"Longitude":78.2891053,"STATE LGD":36,"DISTRICT LGD":699,"BLOCK LGD":4682,"STATE":"Telangana","DISTRICT":"Kumuram Bheem -Asifabad"},{"BLOCK":"Tirla","Latitude":22.5901732,"Longitude":75.2134303,"STATE LGD":23,"DISTRICT LGD":403,"BLOCK LGD":3827,"STATE":"Madhya Pradesh","DISTRICT":"Dhar"},{"BLOCK":"Tiruchuli","Latitude":9.5344105,"Longitude":78.196932,"STATE LGD":33,"DISTRICT LGD":597,"BLOCK LGD":6482,"STATE":"Tamil Nadu","DISTRICT":"Virudhunagar"},{"BLOCK":"Tissa","Latitude":32.8304648,"Longitude":76.1400111,"STATE LGD":2,"DISTRICT LGD":16,"BLOCK LGD":144,"STATE":"Himachal Pradesh","DISTRICT":"Chamba"},{"BLOCK":"Tokapal","Latitude":32.8304648,"Longitude":76.1400111,"STATE LGD":22,"DISTRICT LGD":374,"BLOCK LGD":3603,"STATE":"Chhattisgarh","DISTRICT":"Bastar"},{"BLOCK":"Tonto","Latitude":22.5826844,"Longitude":85.7933302,"STATE LGD":20,"DISTRICT LGD":343,"BLOCK LGD":3275,"STATE":"Jharkhand","DISTRICT":"West Singhbhum"},{"BLOCK":"Tuibong","Latitude":24.360602,"Longitude":93.6990987,"STATE LGD":14,"DISTRICT LGD":254,"BLOCK LGD":6578,"STATE":"Manipur","DISTRICT":"Churachandpur"},{"BLOCK":"Tulail","Latitude":34.5559553,"Longitude":75.0437128,"STATE LGD":1,"DISTRICT LGD":623,"BLOCK LGD":6545,"STATE":"Jammu & Kashmir","DISTRICT":"Bandipora"},{"BLOCK":"Tumudibandh","Latitude":19.9611163,"Longitude":83.6909471,"STATE LGD":21,"DISTRICT LGD":359,"BLOCK LGD":3433,"STATE":"Odisha","DISTRICT":"Kandhamal"},{"BLOCK":"Turaiyur","Latitude":11.2203714,"Longitude":78.4178819,"STATE LGD":33,"DISTRICT LGD":591,"BLOCK LGD":6381,"STATE":"Tamil Nadu","DISTRICT":"Tiruchirappalli"},{"BLOCK":"Uchkagaon","Latitude":26.5468124,"Longitude":84.3101227,"STATE LGD":10,"DISTRICT LGD":197,"BLOCK LGD":1769,"STATE":"Bihar","DISTRICT":"Gopalganj"},{"BLOCK":"Udaigarh","Latitude":22.4148576,"Longitude":74.5601659,"STATE LGD":23,"DISTRICT LGD":639,"BLOCK LGD":3884,"STATE":"Madhya Pradesh","DISTRICT":"Alirajpur"},{"BLOCK":"Umling","Latitude":25.9709746,"Longitude":91.8467813,"STATE LGD":17,"DISTRICT LGD":276,"BLOCK LGD":2469,"STATE":"Meghalaya","DISTRICT":"Ri Bhoi"},{"BLOCK":"Usoor","Latitude":18.4919742,"Longitude":80.859393,"STATE LGD":22,"DISTRICT LGD":636,"BLOCK LGD":3624,"STATE":"Chhattisgarh","DISTRICT":"Bijapur"},{"BLOCK":"Vadagera","Latitude":16.5858232,"Longitude":77.0327699,"STATE LGD":29,"DISTRICT LGD":635,"BLOCK LGD":7389,"STATE":"Karnataka","DISTRICT":"Yadgir"},{"BLOCK":"Varachakwar","Latitude":25.7243591,"Longitude":83.7998852,"STATE LGD":9,"DISTRICT LGD":146,"BLOCK LGD":1150,"STATE":"Uttar Pradesh","DISTRICT":"Ghazipur"},{"BLOCK":"Vijaypur","Latitude":26.0537074,"Longitude":77.3576759,"STATE LGD":23,"DISTRICT LGD":431,"BLOCK LGD":4010,"STATE":"Madhya Pradesh","DISTRICT":"Sheopur"},{"BLOCK":"Vikramgad","Latitude":19.7959651,"Longitude":73.0921035,"STATE LGD":27,"DISTRICT LGD":665,"BLOCK LGD":4602,"STATE":"Maharashtra","DISTRICT":"Palghar"},{"BLOCK":"Virno","Latitude":25.7139423,"Longitude":83.5168754,"STATE LGD":9,"DISTRICT LGD":146,"BLOCK LGD":1151,"STATE":"Uttar Pradesh","DISTRICT":"Ghazipur"},{"BLOCK":"Vishunpura","Latitude":26.1617667,"Longitude":82.2074507,"STATE LGD":9,"DISTRICT LGD":160,"BLOCK LGD":1322,"STATE":"Uttar Pradesh","DISTRICT":"Kushi Nagar"},{"BLOCK":"Wadwani","Latitude":18.9905405,"Longitude":76.035862,"STATE LGD":27,"DISTRICT LGD":470,"BLOCK LGD":4331,"STATE":"Maharashtra","DISTRICT":"Beed"},{"BLOCK":"Wazirganj","Latitude":24.8028968,"Longitude":85.2332919,"STATE LGD":10,"DISTRICT LGD":196,"BLOCK LGD":1755,"STATE":"Bihar","DISTRICT":"Gaya"},{"BLOCK":"Weir","Latitude":27.0123281,"Longitude":77.1518197,"STATE LGD":8,"DISTRICT LGD":91,"BLOCK LGD":619,"STATE":"Rajasthan","DISTRICT":"Bharatpur"},{"BLOCK":"Y. Ramavaram","Latitude":17.6780961,"Longitude":82.377697,"STATE LGD":28,"DISTRICT LGD":745,"BLOCK LGD":4920,"STATE":"Andhra Pradesh","DISTRICT":"Alluri Sitharama Raju"},{"BLOCK":"Yerragondapalem","Latitude":16.0379559,"Longitude":79.298973,"STATE LGD":28,"DISTRICT LGD":517,"BLOCK LGD":5508,"STATE":"Andhra Pradesh","DISTRICT":"Prakasam"},{"BLOCK":"Zari Jamni","Latitude":19.8700399,"Longitude":78.7188602,"STATE LGD":27,"DISTRICT LGD":500,"BLOCK LGD":4633,"STATE":"Maharashtra","DISTRICT":"Yavatmal"},{"BLOCK":"Ziranya","Latitude":21.6122146,"Longitude":75.6164192,"STATE LGD":23,"DISTRICT LGD":414,"BLOCK LGD":3899,"STATE":"Madhya Pradesh","DISTRICT":"Khargone"},{"BLOCK":"Zirapur","Latitude":24.0771791,"Longitude":76.7033471,"STATE LGD":23,"DISTRICT LGD":422,"BLOCK LGD":3947,"STATE":"Madhya Pradesh","DISTRICT":"Rajgarh"},{"BLOCK":"Chausa","Latitude":25.532957,"Longitude":87.0239635,"STATE LGD":10,"DISTRICT LGD":205,"BLOCK LGD":1837,"STATE":"Bihar","DISTRICT":"Madhepura"},{"BLOCK":"Shambhuganj","Latitude":25.0804726,"Longitude":86.7191326,"STATE LGD":10,"DISTRICT LGD":190,"BLOCK LGD":1654,"STATE":"Bihar","DISTRICT":"Banka"}]}
